<?xml version="1.0" encoding="ISO-8859-1" ?>
<ROOT DATABASE="autores.dbf">
  <Structure>
  <Field>
  <Field_name>AUCATEGOR</Field_name>
  <Field_type>Character</Field_type>
  <Field_length>         1</Field_length>
  <Field_decimals>         0</Field_decimals>
  </Field>
  <Field>
  <Field_name>AUNOMBRE</Field_name>
  <Field_type>Character</Field_type>
  <Field_length>        60</Field_length>
  <Field_decimals>         0</Field_decimals>
  </Field>
  <Field>
  <Field_name>AUMATERIA</Field_name>
  <Field_type>Character</Field_type>
  <Field_length>        30</Field_length>
  <Field_decimals>         0</Field_decimals>
  </Field>
  <Field>
  <Field_name>AUNOTAS</Field_name>
  <Field_type>Character</Field_type>
  <Field_length>       255</Field_length>
  <Field_decimals>         0</Field_decimals>
  </Field>
  <Field>
  <Field_name>AUDIRECC</Field_name>
  <Field_type>Character</Field_type>
  <Field_length>        50</Field_length>
  <Field_decimals>         0</Field_decimals>
  </Field>
  <Field>
  <Field_name>AUTELEFONO</Field_name>
  <Field_type>Character</Field_type>
  <Field_length>        30</Field_length>
  <Field_decimals>         0</Field_decimals>
  </Field>
  <Field>
  <Field_name>AULOCALI</Field_name>
  <Field_type>Character</Field_type>
  <Field_length>        50</Field_length>
  <Field_decimals>         0</Field_decimals>
  </Field>
  <Field>
  <Field_name>AUPAIS</Field_name>
  <Field_type>Character</Field_type>
  <Field_length>        30</Field_length>
  <Field_decimals>         0</Field_decimals>
  </Field>
  <Field>
  <Field_name>AUEMAIL</Field_name>
  <Field_type>Character</Field_type>
  <Field_length>        50</Field_length>
  <Field_decimals>         0</Field_decimals>
  </Field>
  <Field>
  <Field_name>AUURL</Field_name>
  <Field_type>Character</Field_type>
  <Field_length>        50</Field_length>
  <Field_decimals>         0</Field_decimals>
  </Field>
  </Structure>
  <Data>
  <Record>
    <AUCATEGOR>E</AUCATEGOR>
    <AUNOMBRE>David Siegel</AUNOMBRE>
    <AUMATERIA></AUMATERIA>
    <AUNOTAS></AUNOTAS>
    <AUDIRECC></AUDIRECC>
    <AUTELEFONO></AUTELEFONO>
    <AULOCALI></AULOCALI>
    <AUPAIS></AUPAIS>
    <AUEMAIL>dsiegel@killersites.com</AUEMAIL>
    <AUURL>http://www.killersites.com</AUURL>
  </Record>
  <Record>
    <AUCATEGOR>C</AUCATEGOR>
    <AUNOMBRE>Chris Spheeris</AUNOMBRE>
    <AUMATERIA>NUEVAS MUSICAS</AUMATERIA>
    <AUNOTAS></AUNOTAS>
    <AUDIRECC></AUDIRECC>
    <AUTELEFONO></AUTELEFONO>
    <AULOCALI></AULOCALI>
    <AUPAIS></AUPAIS>
    <AUEMAIL></AUEMAIL>
    <AUURL></AUURL>
  </Record>
  <Record>
    <AUCATEGOR>E</AUCATEGOR>
    <AUNOMBRE>Mary Bouton</AUNOMBRE>
    <AUMATERIA></AUMATERIA>
    <AUNOTAS></AUNOTAS>
    <AUDIRECC></AUDIRECC>
    <AUTELEFONO></AUTELEFONO>
    <AULOCALI></AULOCALI>
    <AUPAIS></AUPAIS>
    <AUEMAIL></AUEMAIL>
    <AUURL>http://www.thebouttons.com</AUURL>
  </Record>
  <Record>
    <AUCATEGOR>I</AUCATEGOR>
    <AUNOMBRE>Camerata Meiga</AUNOMBRE>
    <AUMATERIA>MUSICA CELTA</AUMATERIA>
    <AUNOTAS></AUNOTAS>
    <AUDIRECC></AUDIRECC>
    <AUTELEFONO></AUTELEFONO>
    <AULOCALI></AULOCALI>
    <AUPAIS></AUPAIS>
    <AUEMAIL></AUEMAIL>
    <AUURL></AUURL>
  </Record>
  <Record>
    <AUCATEGOR>I</AUCATEGOR>
    <AUNOMBRE>Chris Spheeris</AUNOMBRE>
    <AUMATERIA>MULTIINSTRUMENTISTAS</AUMATERIA>
    <AUNOTAS></AUNOTAS>
    <AUDIRECC></AUDIRECC>
    <AUTELEFONO></AUTELEFONO>
    <AULOCALI></AULOCALI>
    <AUPAIS></AUPAIS>
    <AUEMAIL></AUEMAIL>
    <AUURL>http://www.essence-rec.com</AUURL>
  </Record>
  <Record>
    <AUCATEGOR>I</AUCATEGOR>
    <AUNOMBRE>The Corrs</AUNOMBRE>
    <AUMATERIA>MUSICA CELTA</AUMATERIA>
    <AUNOTAS></AUNOTAS>
    <AUDIRECC></AUDIRECC>
    <AUTELEFONO></AUTELEFONO>
    <AULOCALI></AULOCALI>
    <AUPAIS></AUPAIS>
    <AUEMAIL></AUEMAIL>
    <AUURL></AUURL>
  </Record>
  <Record>
    <AUCATEGOR>I</AUCATEGOR>
    <AUNOMBRE>Capercaillie</AUNOMBRE>
    <AUMATERIA>MUSICA CELTA</AUMATERIA>
    <AUNOTAS></AUNOTAS>
    <AUDIRECC></AUDIRECC>
    <AUTELEFONO></AUTELEFONO>
    <AULOCALI></AULOCALI>
    <AUPAIS></AUPAIS>
    <AUEMAIL></AUEMAIL>
    <AUURL></AUURL>
  </Record>
  <Record>
    <AUCATEGOR>I</AUCATEGOR>
    <AUNOMBRE>David Arkenstone</AUNOMBRE>
    <AUMATERIA>MULTIINSTRUMENTISTAS</AUMATERIA>
    <AUNOTAS></AUNOTAS>
    <AUDIRECC></AUDIRECC>
    <AUTELEFONO></AUTELEFONO>
    <AULOCALI></AULOCALI>
    <AUPAIS></AUPAIS>
    <AUEMAIL></AUEMAIL>
    <AUURL></AUURL>
  </Record>
  <Record>
    <AUCATEGOR>I</AUCATEGOR>
    <AUNOMBRE>Loreena McKennit</AUNOMBRE>
    <AUMATERIA>MUSICA CELTA</AUMATERIA>
    <AUNOTAS></AUNOTAS>
    <AUDIRECC></AUDIRECC>
    <AUTELEFONO></AUTELEFONO>
    <AULOCALI></AULOCALI>
    <AUPAIS></AUPAIS>
    <AUEMAIL></AUEMAIL>
    <AUURL></AUURL>
  </Record>
  <Record>
    <AUCATEGOR>I</AUCATEGOR>
    <AUNOMBRE>Angel Illarramendi</AUNOMBRE>
    <AUMATERIA>B.S.O.</AUMATERIA>
    <AUNOTAS></AUNOTAS>
    <AUDIRECC></AUDIRECC>
    <AUTELEFONO></AUTELEFONO>
    <AULOCALI></AULOCALI>
    <AUPAIS></AUPAIS>
    <AUEMAIL></AUEMAIL>
    <AUURL></AUURL>
  </Record>
  <Record>
    <AUCATEGOR>I</AUCATEGOR>
    <AUNOMBRE>James Galway</AUNOMBRE>
    <AUMATERIA>MUSICA CELTA</AUMATERIA>
    <AUNOTAS></AUNOTAS>
    <AUDIRECC></AUDIRECC>
    <AUTELEFONO></AUTELEFONO>
    <AULOCALI></AULOCALI>
    <AUPAIS></AUPAIS>
    <AUEMAIL></AUEMAIL>
    <AUURL></AUURL>
  </Record>
  <Record>
    <AUCATEGOR>I</AUCATEGOR>
    <AUNOMBRE>Ray Lynch</AUNOMBRE>
    <AUMATERIA>MUSICA ELECTRONICA</AUMATERIA>
    <AUNOTAS></AUNOTAS>
    <AUDIRECC></AUDIRECC>
    <AUTELEFONO></AUTELEFONO>
    <AULOCALI></AULOCALI>
    <AUPAIS></AUPAIS>
    <AUEMAIL></AUEMAIL>
    <AUURL></AUURL>
  </Record>
  <Record>
    <AUCATEGOR>I</AUCATEGOR>
    <AUNOMBRE>Tomás Sán Miguel</AUNOMBRE>
    <AUMATERIA>NUEVAS MUSICAS</AUMATERIA>
    <AUNOTAS></AUNOTAS>
    <AUDIRECC></AUDIRECC>
    <AUTELEFONO></AUTELEFONO>
    <AULOCALI></AULOCALI>
    <AUPAIS></AUPAIS>
    <AUEMAIL></AUEMAIL>
    <AUURL></AUURL>
  </Record>
  <Record>
    <AUCATEGOR>I</AUCATEGOR>
    <AUNOMBRE>Nightnoise</AUNOMBRE>
    <AUMATERIA>MUSICA CELTA</AUMATERIA>
    <AUNOTAS></AUNOTAS>
    <AUDIRECC></AUDIRECC>
    <AUTELEFONO></AUTELEFONO>
    <AULOCALI></AULOCALI>
    <AUPAIS></AUPAIS>
    <AUEMAIL></AUEMAIL>
    <AUURL></AUURL>
  </Record>
  <Record>
    <AUCATEGOR>I</AUCATEGOR>
    <AUNOMBRE>Carlos Nuñez</AUNOMBRE>
    <AUMATERIA>MUSICA CELTA</AUMATERIA>
    <AUNOTAS></AUNOTAS>
    <AUDIRECC></AUDIRECC>
    <AUTELEFONO></AUTELEFONO>
    <AULOCALI></AULOCALI>
    <AUPAIS></AUPAIS>
    <AUEMAIL></AUEMAIL>
    <AUURL></AUURL>
  </Record>
  <Record>
    <AUCATEGOR>I</AUCATEGOR>
    <AUNOMBRE>Alex de Grassi</AUNOMBRE>
    <AUMATERIA>NUEVAS MUSICAS</AUMATERIA>
    <AUNOTAS></AUNOTAS>
    <AUDIRECC></AUDIRECC>
    <AUTELEFONO></AUTELEFONO>
    <AULOCALI></AULOCALI>
    <AUPAIS></AUPAIS>
    <AUEMAIL></AUEMAIL>
    <AUURL></AUURL>
  </Record>
  <Record>
    <AUCATEGOR>I</AUCATEGOR>
    <AUNOMBRE>Liz Story</AUNOMBRE>
    <AUMATERIA>NUEVAS MUSICAS</AUMATERIA>
    <AUNOTAS></AUNOTAS>
    <AUDIRECC></AUDIRECC>
    <AUTELEFONO></AUTELEFONO>
    <AULOCALI></AULOCALI>
    <AUPAIS></AUPAIS>
    <AUEMAIL></AUEMAIL>
    <AUURL></AUURL>
  </Record>
  <Record>
    <AUCATEGOR>I</AUCATEGOR>
    <AUNOMBRE>VV.AA. Whindham Hill</AUNOMBRE>
    <AUMATERIA>NUEVAS MUSICAS</AUMATERIA>
    <AUNOTAS></AUNOTAS>
    <AUDIRECC></AUDIRECC>
    <AUTELEFONO></AUTELEFONO>
    <AULOCALI></AULOCALI>
    <AUPAIS></AUPAIS>
    <AUEMAIL></AUEMAIL>
    <AUURL></AUURL>
  </Record>
  <Record>
    <AUCATEGOR>I</AUCATEGOR>
    <AUNOMBRE>George Winston</AUNOMBRE>
    <AUMATERIA>NUEVAS MUSICAS</AUMATERIA>
    <AUNOTAS></AUNOTAS>
    <AUDIRECC></AUDIRECC>
    <AUTELEFONO></AUTELEFONO>
    <AULOCALI></AULOCALI>
    <AUPAIS></AUPAIS>
    <AUEMAIL></AUEMAIL>
    <AUURL></AUURL>
  </Record>
  <Record>
    <AUCATEGOR>I</AUCATEGOR>
    <AUNOMBRE>Yanni</AUNOMBRE>
    <AUMATERIA>SINTESISTAS</AUMATERIA>
    <AUNOTAS></AUNOTAS>
    <AUDIRECC></AUDIRECC>
    <AUTELEFONO></AUTELEFONO>
    <AULOCALI></AULOCALI>
    <AUPAIS></AUPAIS>
    <AUEMAIL></AUEMAIL>
    <AUURL></AUURL>
  </Record>
  <Record>
    <AUCATEGOR>E</AUCATEGOR>
    <AUNOMBRE>Joel Spolsky</AUNOMBRE>
    <AUMATERIA></AUMATERIA>
    <AUNOTAS></AUNOTAS>
    <AUDIRECC></AUDIRECC>
    <AUTELEFONO></AUTELEFONO>
    <AULOCALI></AULOCALI>
    <AUPAIS></AUPAIS>
    <AUEMAIL>spolsky@manix.com</AUEMAIL>
    <AUURL>http://www.joelonsoftware.com</AUURL>
  </Record>
  <Record>
    <AUCATEGOR>E</AUCATEGOR>
    <AUNOMBRE>E. Yourdon</AUNOMBRE>
    <AUMATERIA></AUMATERIA>
    <AUNOTAS></AUNOTAS>
    <AUDIRECC></AUDIRECC>
    <AUTELEFONO></AUTELEFONO>
    <AULOCALI></AULOCALI>
    <AUPAIS></AUPAIS>
    <AUEMAIL></AUEMAIL>
    <AUURL></AUURL>
  </Record>
  <Record>
    <AUCATEGOR>E</AUCATEGOR>
    <AUNOMBRE>J.R.R. Tolkien</AUNOMBRE>
    <AUMATERIA></AUMATERIA>
    <AUNOTAS></AUNOTAS>
    <AUDIRECC></AUDIRECC>
    <AUTELEFONO></AUTELEFONO>
    <AULOCALI></AULOCALI>
    <AUPAIS></AUPAIS>
    <AUEMAIL></AUEMAIL>
    <AUURL></AUURL>
  </Record>
  <Record>
    <AUCATEGOR>E</AUCATEGOR>
    <AUNOMBRE>l. hay</AUNOMBRE>
    <AUMATERIA></AUMATERIA>
    <AUNOTAS></AUNOTAS>
    <AUDIRECC></AUDIRECC>
    <AUTELEFONO></AUTELEFONO>
    <AULOCALI></AULOCALI>
    <AUPAIS></AUPAIS>
    <AUEMAIL></AUEMAIL>
    <AUURL></AUURL>
  </Record>
  <Record>
    <AUCATEGOR>E</AUCATEGOR>
    <AUNOMBRE>Karlos Arguiñano</AUNOMBRE>
    <AUMATERIA></AUMATERIA>
    <AUNOTAS></AUNOTAS>
    <AUDIRECC></AUDIRECC>
    <AUTELEFONO></AUTELEFONO>
    <AULOCALI></AULOCALI>
    <AUPAIS></AUPAIS>
    <AUEMAIL></AUEMAIL>
    <AUURL></AUURL>
  </Record>
  <Record>
    <AUCATEGOR>E</AUCATEGOR>
    <AUNOMBRE>Decoroso Crespo</AUNOMBRE>
    <AUMATERIA></AUMATERIA>
    <AUNOTAS></AUNOTAS>
    <AUDIRECC></AUDIRECC>
    <AUTELEFONO></AUTELEFONO>
    <AULOCALI></AULOCALI>
    <AUPAIS></AUPAIS>
    <AUEMAIL></AUEMAIL>
    <AUURL></AUURL>
  </Record>
  <Record>
    <AUCATEGOR>E</AUCATEGOR>
    <AUNOMBRE>jose luis sanchez navarro</AUNOMBRE>
    <AUMATERIA></AUMATERIA>
    <AUNOTAS></AUNOTAS>
    <AUDIRECC></AUDIRECC>
    <AUTELEFONO></AUTELEFONO>
    <AULOCALI></AULOCALI>
    <AUPAIS></AUPAIS>
    <AUEMAIL></AUEMAIL>
    <AUURL></AUURL>
  </Record>
  <Record>
    <AUCATEGOR>E</AUCATEGOR>
    <AUNOMBRE>i.b.m.</AUNOMBRE>
    <AUMATERIA></AUMATERIA>
    <AUNOTAS></AUNOTAS>
    <AUDIRECC></AUDIRECC>
    <AUTELEFONO></AUTELEFONO>
    <AULOCALI></AULOCALI>
    <AUPAIS></AUPAIS>
    <AUEMAIL></AUEMAIL>
    <AUURL></AUURL>
  </Record>
  <Record>
    <AUCATEGOR>E</AUCATEGOR>
    <AUNOMBRE>e. de manuel torres</AUNOMBRE>
    <AUMATERIA></AUMATERIA>
    <AUNOTAS></AUNOTAS>
    <AUDIRECC></AUDIRECC>
    <AUTELEFONO></AUTELEFONO>
    <AULOCALI></AULOCALI>
    <AUPAIS></AUPAIS>
    <AUEMAIL></AUEMAIL>
    <AUURL></AUURL>
  </Record>
  <Record>
    <AUCATEGOR>E</AUCATEGOR>
    <AUNOMBRE>p. albertos</AUNOMBRE>
    <AUMATERIA></AUMATERIA>
    <AUNOTAS></AUNOTAS>
    <AUDIRECC></AUDIRECC>
    <AUTELEFONO></AUTELEFONO>
    <AULOCALI></AULOCALI>
    <AUPAIS></AUPAIS>
    <AUEMAIL></AUEMAIL>
    <AUURL></AUURL>
  </Record>
  <Record>
    <AUCATEGOR>E</AUCATEGOR>
    <AUNOMBRE>j.l. manglano</AUNOMBRE>
    <AUMATERIA></AUMATERIA>
    <AUNOTAS></AUNOTAS>
    <AUDIRECC></AUDIRECC>
    <AUTELEFONO></AUTELEFONO>
    <AULOCALI></AULOCALI>
    <AUPAIS></AUPAIS>
    <AUEMAIL></AUEMAIL>
    <AUURL></AUURL>
  </Record>
  <Record>
    <AUCATEGOR>E</AUCATEGOR>
    <AUNOMBRE>C.J. Date</AUNOMBRE>
    <AUMATERIA></AUMATERIA>
    <AUNOTAS></AUNOTAS>
    <AUDIRECC></AUDIRECC>
    <AUTELEFONO></AUTELEFONO>
    <AULOCALI></AULOCALI>
    <AUPAIS></AUPAIS>
    <AUEMAIL></AUEMAIL>
    <AUURL></AUURL>
  </Record>
  <Record>
    <AUCATEGOR>E</AUCATEGOR>
    <AUNOMBRE>g. booch</AUNOMBRE>
    <AUMATERIA></AUMATERIA>
    <AUNOTAS></AUNOTAS>
    <AUDIRECC></AUDIRECC>
    <AUTELEFONO></AUTELEFONO>
    <AULOCALI></AULOCALI>
    <AUPAIS></AUPAIS>
    <AUEMAIL></AUEMAIL>
    <AUURL></AUURL>
  </Record>
  <Record>
    <AUCATEGOR>E</AUCATEGOR>
    <AUNOMBRE>h. mintzberg</AUNOMBRE>
    <AUMATERIA></AUMATERIA>
    <AUNOTAS></AUNOTAS>
    <AUDIRECC></AUDIRECC>
    <AUTELEFONO></AUTELEFONO>
    <AULOCALI></AULOCALI>
    <AUPAIS></AUPAIS>
    <AUEMAIL></AUEMAIL>
    <AUURL></AUURL>
  </Record>
  <Record>
    <AUCATEGOR>E</AUCATEGOR>
    <AUNOMBRE>M. Covadonga Fernández</AUNOMBRE>
    <AUMATERIA></AUMATERIA>
    <AUNOTAS></AUNOTAS>
    <AUDIRECC></AUDIRECC>
    <AUTELEFONO></AUTELEFONO>
    <AULOCALI></AULOCALI>
    <AUPAIS></AUPAIS>
    <AUEMAIL></AUEMAIL>
    <AUURL></AUURL>
  </Record>
  <Record>
    <AUCATEGOR>E</AUCATEGOR>
    <AUNOMBRE>j. hopcroft</AUNOMBRE>
    <AUMATERIA></AUMATERIA>
    <AUNOTAS></AUNOTAS>
    <AUDIRECC></AUDIRECC>
    <AUTELEFONO></AUTELEFONO>
    <AULOCALI></AULOCALI>
    <AUPAIS></AUPAIS>
    <AUEMAIL></AUEMAIL>
    <AUURL></AUURL>
  </Record>
  <Record>
    <AUCATEGOR>E</AUCATEGOR>
    <AUNOMBRE>e. horowitz</AUNOMBRE>
    <AUMATERIA></AUMATERIA>
    <AUNOTAS></AUNOTAS>
    <AUDIRECC></AUDIRECC>
    <AUTELEFONO></AUTELEFONO>
    <AULOCALI></AULOCALI>
    <AUPAIS></AUPAIS>
    <AUEMAIL></AUEMAIL>
    <AUURL></AUURL>
  </Record>
  <Record>
    <AUCATEGOR>E</AUCATEGOR>
    <AUNOMBRE>C. Gane</AUNOMBRE>
    <AUMATERIA></AUMATERIA>
    <AUNOTAS></AUNOTAS>
    <AUDIRECC></AUDIRECC>
    <AUTELEFONO></AUTELEFONO>
    <AULOCALI></AULOCALI>
    <AUPAIS></AUPAIS>
    <AUEMAIL></AUEMAIL>
    <AUURL></AUURL>
  </Record>
  <Record>
    <AUCATEGOR>E</AUCATEGOR>
    <AUNOMBRE>j.p. matheron</AUNOMBRE>
    <AUMATERIA></AUMATERIA>
    <AUNOTAS></AUNOTAS>
    <AUDIRECC></AUDIRECC>
    <AUTELEFONO></AUTELEFONO>
    <AULOCALI></AULOCALI>
    <AUPAIS></AUPAIS>
    <AUEMAIL></AUEMAIL>
    <AUURL></AUURL>
  </Record>
  <Record>
    <AUCATEGOR>E</AUCATEGOR>
    <AUNOMBRE>N. Martínez</AUNOMBRE>
    <AUMATERIA></AUMATERIA>
    <AUNOTAS></AUNOTAS>
    <AUDIRECC></AUDIRECC>
    <AUTELEFONO></AUTELEFONO>
    <AULOCALI></AULOCALI>
    <AUPAIS></AUPAIS>
    <AUEMAIL></AUEMAIL>
    <AUURL></AUURL>
  </Record>
  <Record>
    <AUCATEGOR>E</AUCATEGOR>
    <AUNOMBRE>f. sanchis llorca</AUNOMBRE>
    <AUMATERIA></AUMATERIA>
    <AUNOTAS></AUNOTAS>
    <AUDIRECC></AUDIRECC>
    <AUTELEFONO></AUTELEFONO>
    <AULOCALI></AULOCALI>
    <AUPAIS></AUPAIS>
    <AUEMAIL></AUEMAIL>
    <AUURL></AUURL>
  </Record>
  <Record>
    <AUCATEGOR>E</AUCATEGOR>
    <AUNOMBRE>p. bishop</AUNOMBRE>
    <AUMATERIA></AUMATERIA>
    <AUNOTAS></AUNOTAS>
    <AUDIRECC></AUDIRECC>
    <AUTELEFONO></AUTELEFONO>
    <AULOCALI></AULOCALI>
    <AUPAIS></AUPAIS>
    <AUEMAIL></AUEMAIL>
    <AUURL></AUURL>
  </Record>
  <Record>
    <AUCATEGOR>E</AUCATEGOR>
    <AUNOMBRE>g.l. simons</AUNOMBRE>
    <AUMATERIA></AUMATERIA>
    <AUNOTAS></AUNOTAS>
    <AUDIRECC></AUDIRECC>
    <AUTELEFONO></AUTELEFONO>
    <AULOCALI></AULOCALI>
    <AUPAIS></AUPAIS>
    <AUEMAIL></AUEMAIL>
    <AUURL></AUURL>
  </Record>
  <Record>
    <AUCATEGOR>E</AUCATEGOR>
    <AUNOMBRE>j. millman</AUNOMBRE>
    <AUMATERIA></AUMATERIA>
    <AUNOTAS></AUNOTAS>
    <AUDIRECC></AUDIRECC>
    <AUTELEFONO></AUTELEFONO>
    <AULOCALI></AULOCALI>
    <AUPAIS></AUPAIS>
    <AUEMAIL></AUEMAIL>
    <AUURL></AUURL>
  </Record>
  <Record>
    <AUCATEGOR>E</AUCATEGOR>
    <AUNOMBRE>j. mompin</AUNOMBRE>
    <AUMATERIA></AUMATERIA>
    <AUNOTAS></AUNOTAS>
    <AUDIRECC></AUDIRECC>
    <AUTELEFONO></AUTELEFONO>
    <AULOCALI></AULOCALI>
    <AUPAIS></AUPAIS>
    <AUEMAIL></AUEMAIL>
    <AUURL></AUURL>
  </Record>
  <Record>
    <AUCATEGOR>E</AUCATEGOR>
    <AUNOMBRE>M. Shallis</AUNOMBRE>
    <AUMATERIA></AUMATERIA>
    <AUNOTAS></AUNOTAS>
    <AUDIRECC></AUDIRECC>
    <AUTELEFONO></AUTELEFONO>
    <AULOCALI></AULOCALI>
    <AUPAIS></AUPAIS>
    <AUEMAIL></AUEMAIL>
    <AUURL></AUURL>
  </Record>
  <Record>
    <AUCATEGOR>E</AUCATEGOR>
    <AUNOMBRE>s. gergely</AUNOMBRE>
    <AUMATERIA></AUMATERIA>
    <AUNOTAS></AUNOTAS>
    <AUDIRECC></AUDIRECC>
    <AUTELEFONO></AUTELEFONO>
    <AULOCALI></AULOCALI>
    <AUPAIS></AUPAIS>
    <AUEMAIL></AUEMAIL>
    <AUURL></AUURL>
  </Record>
  <Record>
    <AUCATEGOR>E</AUCATEGOR>
    <AUNOMBRE>s. sahni</AUNOMBRE>
    <AUMATERIA></AUMATERIA>
    <AUNOTAS></AUNOTAS>
    <AUDIRECC></AUDIRECC>
    <AUTELEFONO></AUTELEFONO>
    <AULOCALI></AULOCALI>
    <AUPAIS></AUPAIS>
    <AUEMAIL></AUEMAIL>
    <AUURL></AUURL>
  </Record>
  <Record>
    <AUCATEGOR>E</AUCATEGOR>
    <AUNOMBRE>r. romero</AUNOMBRE>
    <AUMATERIA></AUMATERIA>
    <AUNOTAS></AUNOTAS>
    <AUDIRECC></AUDIRECC>
    <AUTELEFONO></AUTELEFONO>
    <AULOCALI></AULOCALI>
    <AUPAIS></AUPAIS>
    <AUEMAIL></AUEMAIL>
    <AUURL></AUURL>
  </Record>
  <Record>
    <AUCATEGOR>E</AUCATEGOR>
    <AUNOMBRE>s. balasch parisi</AUNOMBRE>
    <AUMATERIA></AUMATERIA>
    <AUNOTAS></AUNOTAS>
    <AUDIRECC></AUDIRECC>
    <AUTELEFONO></AUTELEFONO>
    <AULOCALI></AULOCALI>
    <AUPAIS></AUPAIS>
    <AUEMAIL></AUEMAIL>
    <AUURL></AUURL>
  </Record>
  <Record>
    <AUCATEGOR>E</AUCATEGOR>
    <AUNOMBRE>jose l. sanchez navarro</AUNOMBRE>
    <AUMATERIA></AUMATERIA>
    <AUNOTAS></AUNOTAS>
    <AUDIRECC></AUDIRECC>
    <AUTELEFONO></AUTELEFONO>
    <AULOCALI></AULOCALI>
    <AUPAIS></AUPAIS>
    <AUEMAIL></AUEMAIL>
    <AUURL></AUURL>
  </Record>
  <Record>
    <AUCATEGOR>E</AUCATEGOR>
    <AUNOMBRE>f. lario esteban</AUNOMBRE>
    <AUMATERIA></AUMATERIA>
    <AUNOTAS></AUNOTAS>
    <AUDIRECC></AUDIRECC>
    <AUTELEFONO></AUTELEFONO>
    <AULOCALI></AULOCALI>
    <AUPAIS></AUPAIS>
    <AUEMAIL></AUEMAIL>
    <AUURL></AUURL>
  </Record>
  <Record>
    <AUCATEGOR>E</AUCATEGOR>
    <AUNOMBRE>s. manrique</AUNOMBRE>
    <AUMATERIA></AUMATERIA>
    <AUNOTAS></AUNOTAS>
    <AUDIRECC></AUDIRECC>
    <AUTELEFONO></AUTELEFONO>
    <AULOCALI></AULOCALI>
    <AUPAIS></AUPAIS>
    <AUEMAIL></AUEMAIL>
    <AUURL></AUURL>
  </Record>
  <Record>
    <AUCATEGOR>E</AUCATEGOR>
    <AUNOMBRE>j. etayo</AUNOMBRE>
    <AUMATERIA></AUMATERIA>
    <AUNOTAS></AUNOTAS>
    <AUDIRECC></AUDIRECC>
    <AUTELEFONO></AUTELEFONO>
    <AULOCALI></AULOCALI>
    <AUPAIS></AUPAIS>
    <AUEMAIL></AUEMAIL>
    <AUURL></AUURL>
  </Record>
  <Record>
    <AUCATEGOR>E</AUCATEGOR>
    <AUNOMBRE>e. tebar flores</AUNOMBRE>
    <AUMATERIA></AUMATERIA>
    <AUNOTAS></AUNOTAS>
    <AUDIRECC></AUDIRECC>
    <AUTELEFONO></AUTELEFONO>
    <AULOCALI></AULOCALI>
    <AUPAIS></AUPAIS>
    <AUEMAIL></AUEMAIL>
    <AUURL></AUURL>
  </Record>
  <Record>
    <AUCATEGOR>E</AUCATEGOR>
    <AUNOMBRE>j. alvarez lopez</AUNOMBRE>
    <AUMATERIA></AUMATERIA>
    <AUNOTAS></AUNOTAS>
    <AUDIRECC></AUDIRECC>
    <AUTELEFONO></AUTELEFONO>
    <AULOCALI></AULOCALI>
    <AUPAIS></AUPAIS>
    <AUEMAIL></AUEMAIL>
    <AUURL></AUURL>
  </Record>
  <Record>
    <AUCATEGOR>E</AUCATEGOR>
    <AUNOMBRE>j. alvarez flores</AUNOMBRE>
    <AUMATERIA></AUMATERIA>
    <AUNOTAS></AUNOTAS>
    <AUDIRECC></AUDIRECC>
    <AUTELEFONO></AUTELEFONO>
    <AULOCALI></AULOCALI>
    <AUPAIS></AUPAIS>
    <AUEMAIL></AUEMAIL>
    <AUURL></AUURL>
  </Record>
  <Record>
    <AUCATEGOR>E</AUCATEGOR>
    <AUNOMBRE>mº economia y hacienda</AUNOMBRE>
    <AUMATERIA></AUMATERIA>
    <AUNOTAS></AUNOTAS>
    <AUDIRECC></AUDIRECC>
    <AUTELEFONO></AUTELEFONO>
    <AULOCALI></AULOCALI>
    <AUPAIS></AUPAIS>
    <AUEMAIL></AUEMAIL>
    <AUURL></AUURL>
  </Record>
  <Record>
    <AUCATEGOR>E</AUCATEGOR>
    <AUNOMBRE>p. dilascia</AUNOMBRE>
    <AUMATERIA></AUMATERIA>
    <AUNOTAS></AUNOTAS>
    <AUDIRECC></AUDIRECC>
    <AUTELEFONO></AUTELEFONO>
    <AULOCALI></AULOCALI>
    <AUPAIS></AUPAIS>
    <AUEMAIL></AUEMAIL>
    <AUURL></AUURL>
  </Record>
  <Record>
    <AUCATEGOR>E</AUCATEGOR>
    <AUNOMBRE>Diario El Pais</AUNOMBRE>
    <AUMATERIA></AUMATERIA>
    <AUNOTAS></AUNOTAS>
    <AUDIRECC></AUDIRECC>
    <AUTELEFONO></AUTELEFONO>
    <AULOCALI></AULOCALI>
    <AUPAIS></AUPAIS>
    <AUEMAIL></AUEMAIL>
    <AUURL></AUURL>
  </Record>
  <Record>
    <AUCATEGOR>E</AUCATEGOR>
    <AUNOMBRE>m. king</AUNOMBRE>
    <AUMATERIA></AUMATERIA>
    <AUNOTAS></AUNOTAS>
    <AUDIRECC></AUDIRECC>
    <AUTELEFONO></AUTELEFONO>
    <AULOCALI></AULOCALI>
    <AUPAIS></AUPAIS>
    <AUEMAIL></AUEMAIL>
    <AUURL></AUURL>
  </Record>
  <Record>
    <AUCATEGOR>E</AUCATEGOR>
    <AUNOMBRE>s. gawain</AUNOMBRE>
    <AUMATERIA></AUMATERIA>
    <AUNOTAS></AUNOTAS>
    <AUDIRECC></AUDIRECC>
    <AUTELEFONO></AUTELEFONO>
    <AULOCALI></AULOCALI>
    <AUPAIS></AUPAIS>
    <AUEMAIL></AUEMAIL>
    <AUURL></AUURL>
  </Record>
  <Record>
    <AUCATEGOR>E</AUCATEGOR>
    <AUNOMBRE>i.m.p.i.</AUNOMBRE>
    <AUMATERIA></AUMATERIA>
    <AUNOTAS></AUNOTAS>
    <AUDIRECC></AUDIRECC>
    <AUTELEFONO></AUTELEFONO>
    <AULOCALI></AULOCALI>
    <AUPAIS></AUPAIS>
    <AUEMAIL></AUEMAIL>
    <AUURL></AUURL>
  </Record>
  <Record>
    <AUCATEGOR>E</AUCATEGOR>
    <AUNOMBRE>u. howenstein</AUNOMBRE>
    <AUMATERIA></AUMATERIA>
    <AUNOTAS></AUNOTAS>
    <AUDIRECC></AUDIRECC>
    <AUTELEFONO></AUTELEFONO>
    <AULOCALI></AULOCALI>
    <AUPAIS></AUPAIS>
    <AUEMAIL></AUEMAIL>
    <AUURL></AUURL>
  </Record>
  <Record>
    <AUCATEGOR>E</AUCATEGOR>
    <AUNOMBRE>L. Mondejar</AUNOMBRE>
    <AUMATERIA></AUMATERIA>
    <AUNOTAS></AUNOTAS>
    <AUDIRECC></AUDIRECC>
    <AUTELEFONO></AUTELEFONO>
    <AULOCALI></AULOCALI>
    <AUPAIS></AUPAIS>
    <AUEMAIL></AUEMAIL>
    <AUURL></AUURL>
  </Record>
  <Record>
    <AUCATEGOR>E</AUCATEGOR>
    <AUNOMBRE>t. teorey</AUNOMBRE>
    <AUMATERIA></AUMATERIA>
    <AUNOTAS></AUNOTAS>
    <AUDIRECC></AUDIRECC>
    <AUTELEFONO></AUTELEFONO>
    <AULOCALI></AULOCALI>
    <AUPAIS></AUPAIS>
    <AUEMAIL></AUEMAIL>
    <AUURL></AUURL>
  </Record>
  <Record>
    <AUCATEGOR>E</AUCATEGOR>
    <AUNOMBRE>r. hull</AUNOMBRE>
    <AUMATERIA></AUMATERIA>
    <AUNOTAS></AUNOTAS>
    <AUDIRECC></AUDIRECC>
    <AUTELEFONO></AUTELEFONO>
    <AULOCALI></AULOCALI>
    <AUPAIS></AUPAIS>
    <AUEMAIL></AUEMAIL>
    <AUURL></AUURL>
  </Record>
  <Record>
    <AUCATEGOR>E</AUCATEGOR>
    <AUNOMBRE>j. cuena</AUNOMBRE>
    <AUMATERIA></AUMATERIA>
    <AUNOTAS></AUNOTAS>
    <AUDIRECC></AUDIRECC>
    <AUTELEFONO></AUTELEFONO>
    <AULOCALI></AULOCALI>
    <AUPAIS></AUPAIS>
    <AUEMAIL></AUEMAIL>
    <AUURL></AUURL>
  </Record>
  <Record>
    <AUCATEGOR>E</AUCATEGOR>
    <AUNOMBRE>s. coffin</AUNOMBRE>
    <AUMATERIA></AUMATERIA>
    <AUNOTAS></AUNOTAS>
    <AUDIRECC></AUDIRECC>
    <AUTELEFONO></AUTELEFONO>
    <AULOCALI></AULOCALI>
    <AUPAIS></AUPAIS>
    <AUEMAIL></AUEMAIL>
    <AUURL></AUURL>
  </Record>
  <Record>
    <AUCATEGOR>E</AUCATEGOR>
    <AUNOMBRE>r. fairley</AUNOMBRE>
    <AUMATERIA></AUMATERIA>
    <AUNOTAS></AUNOTAS>
    <AUDIRECC></AUDIRECC>
    <AUTELEFONO></AUTELEFONO>
    <AULOCALI></AULOCALI>
    <AUPAIS></AUPAIS>
    <AUEMAIL></AUEMAIL>
    <AUURL></AUURL>
  </Record>
  <Record>
    <AUCATEGOR>E</AUCATEGOR>
    <AUNOMBRE>l. joyanes</AUNOMBRE>
    <AUMATERIA></AUMATERIA>
    <AUNOTAS></AUNOTAS>
    <AUDIRECC></AUDIRECC>
    <AUTELEFONO></AUTELEFONO>
    <AULOCALI></AULOCALI>
    <AUPAIS></AUPAIS>
    <AUEMAIL></AUEMAIL>
    <AUURL></AUURL>
  </Record>
  <Record>
    <AUCATEGOR>E</AUCATEGOR>
    <AUNOMBRE>n. wirth</AUNOMBRE>
    <AUMATERIA></AUMATERIA>
    <AUNOTAS></AUNOTAS>
    <AUDIRECC></AUDIRECC>
    <AUTELEFONO></AUTELEFONO>
    <AULOCALI></AULOCALI>
    <AUPAIS></AUPAIS>
    <AUEMAIL></AUEMAIL>
    <AUURL></AUURL>
  </Record>
  <Record>
    <AUCATEGOR>E</AUCATEGOR>
    <AUNOMBRE>s. madnick</AUNOMBRE>
    <AUMATERIA></AUMATERIA>
    <AUNOTAS></AUNOTAS>
    <AUDIRECC></AUDIRECC>
    <AUTELEFONO></AUTELEFONO>
    <AULOCALI></AULOCALI>
    <AUPAIS></AUPAIS>
    <AUEMAIL></AUEMAIL>
    <AUURL></AUURL>
  </Record>
  <Record>
    <AUCATEGOR>E</AUCATEGOR>
    <AUNOMBRE>B. Kernighan</AUNOMBRE>
    <AUMATERIA></AUMATERIA>
    <AUNOTAS></AUNOTAS>
    <AUDIRECC></AUDIRECC>
    <AUTELEFONO></AUTELEFONO>
    <AULOCALI></AULOCALI>
    <AUPAIS></AUPAIS>
    <AUEMAIL></AUEMAIL>
    <AUURL></AUURL>
  </Record>
  <Record>
    <AUCATEGOR>E</AUCATEGOR>
    <AUNOMBRE>f. barber</AUNOMBRE>
    <AUMATERIA></AUMATERIA>
    <AUNOTAS></AUNOTAS>
    <AUDIRECC></AUDIRECC>
    <AUTELEFONO></AUTELEFONO>
    <AULOCALI></AULOCALI>
    <AUPAIS></AUPAIS>
    <AUEMAIL></AUEMAIL>
    <AUURL></AUURL>
  </Record>
  <Record>
    <AUCATEGOR>E</AUCATEGOR>
    <AUNOMBRE>M. alpuente</AUNOMBRE>
    <AUMATERIA></AUMATERIA>
    <AUNOTAS></AUNOTAS>
    <AUDIRECC></AUDIRECC>
    <AUTELEFONO></AUTELEFONO>
    <AULOCALI></AULOCALI>
    <AUPAIS></AUPAIS>
    <AUEMAIL></AUEMAIL>
    <AUURL></AUURL>
  </Record>
  <Record>
    <AUCATEGOR>E</AUCATEGOR>
    <AUNOMBRE>m. alonso</AUNOMBRE>
    <AUMATERIA></AUMATERIA>
    <AUNOTAS></AUNOTAS>
    <AUDIRECC></AUDIRECC>
    <AUTELEFONO></AUTELEFONO>
    <AULOCALI></AULOCALI>
    <AUPAIS></AUPAIS>
    <AUEMAIL></AUEMAIL>
    <AUURL></AUURL>
  </Record>
  <Record>
    <AUCATEGOR>E</AUCATEGOR>
    <AUNOMBRE>n. nilsson</AUNOMBRE>
    <AUMATERIA></AUMATERIA>
    <AUNOTAS></AUNOTAS>
    <AUDIRECC></AUDIRECC>
    <AUTELEFONO></AUTELEFONO>
    <AULOCALI></AULOCALI>
    <AUPAIS></AUPAIS>
    <AUEMAIL></AUEMAIL>
    <AUURL></AUURL>
  </Record>
  <Record>
    <AUCATEGOR>E</AUCATEGOR>
    <AUNOMBRE>r. kowalski</AUNOMBRE>
    <AUMATERIA></AUMATERIA>
    <AUNOTAS></AUNOTAS>
    <AUDIRECC></AUDIRECC>
    <AUTELEFONO></AUTELEFONO>
    <AULOCALI></AULOCALI>
    <AUPAIS></AUPAIS>
    <AUEMAIL></AUEMAIL>
    <AUURL></AUURL>
  </Record>
  <Record>
    <AUCATEGOR>E</AUCATEGOR>
    <AUNOMBRE>X Castellani</AUNOMBRE>
    <AUMATERIA></AUMATERIA>
    <AUNOTAS></AUNOTAS>
    <AUDIRECC></AUDIRECC>
    <AUTELEFONO></AUTELEFONO>
    <AULOCALI></AULOCALI>
    <AUPAIS></AUPAIS>
    <AUEMAIL></AUEMAIL>
    <AUURL></AUURL>
  </Record>
  <Record>
    <AUCATEGOR>E</AUCATEGOR>
    <AUNOMBRE>X. Castellani</AUNOMBRE>
    <AUMATERIA></AUMATERIA>
    <AUNOTAS></AUNOTAS>
    <AUDIRECC></AUDIRECC>
    <AUTELEFONO></AUTELEFONO>
    <AULOCALI></AULOCALI>
    <AUPAIS></AUPAIS>
    <AUEMAIL></AUEMAIL>
    <AUURL></AUURL>
  </Record>
  <Record>
    <AUCATEGOR>E</AUCATEGOR>
    <AUNOMBRE>d. tsichritzis</AUNOMBRE>
    <AUMATERIA></AUMATERIA>
    <AUNOTAS></AUNOTAS>
    <AUDIRECC></AUDIRECC>
    <AUTELEFONO></AUTELEFONO>
    <AULOCALI></AULOCALI>
    <AUPAIS></AUPAIS>
    <AUEMAIL></AUEMAIL>
    <AUURL></AUURL>
  </Record>
  <Record>
    <AUCATEGOR>E</AUCATEGOR>
    <AUNOMBRE>j. hannan</AUNOMBRE>
    <AUMATERIA></AUMATERIA>
    <AUNOTAS></AUNOTAS>
    <AUDIRECC></AUDIRECC>
    <AUTELEFONO></AUTELEFONO>
    <AULOCALI></AULOCALI>
    <AUPAIS></AUPAIS>
    <AUEMAIL></AUEMAIL>
    <AUURL></AUURL>
  </Record>
  <Record>
    <AUCATEGOR>E</AUCATEGOR>
    <AUNOMBRE>p. blesa</AUNOMBRE>
    <AUMATERIA></AUMATERIA>
    <AUNOTAS></AUNOTAS>
    <AUDIRECC></AUDIRECC>
    <AUTELEFONO></AUTELEFONO>
    <AULOCALI></AULOCALI>
    <AUPAIS></AUPAIS>
    <AUEMAIL></AUEMAIL>
    <AUURL></AUURL>
  </Record>
  <Record>
    <AUCATEGOR>E</AUCATEGOR>
    <AUNOMBRE>j. barnes</AUNOMBRE>
    <AUMATERIA></AUMATERIA>
    <AUNOTAS></AUNOTAS>
    <AUDIRECC></AUDIRECC>
    <AUTELEFONO></AUTELEFONO>
    <AULOCALI></AULOCALI>
    <AUPAIS></AUPAIS>
    <AUEMAIL></AUEMAIL>
    <AUURL></AUURL>
  </Record>
  <Record>
    <AUCATEGOR>E</AUCATEGOR>
    <AUNOMBRE>t. pratt</AUNOMBRE>
    <AUMATERIA></AUMATERIA>
    <AUNOTAS></AUNOTAS>
    <AUDIRECC></AUDIRECC>
    <AUTELEFONO></AUTELEFONO>
    <AULOCALI></AULOCALI>
    <AUPAIS></AUPAIS>
    <AUEMAIL></AUEMAIL>
    <AUURL></AUURL>
  </Record>
  <Record>
    <AUCATEGOR>E</AUCATEGOR>
    <AUNOMBRE>r. presman</AUNOMBRE>
    <AUMATERIA></AUMATERIA>
    <AUNOTAS></AUNOTAS>
    <AUDIRECC></AUDIRECC>
    <AUTELEFONO></AUTELEFONO>
    <AULOCALI></AULOCALI>
    <AUPAIS></AUPAIS>
    <AUEMAIL></AUEMAIL>
    <AUURL></AUURL>
  </Record>
  <Record>
    <AUCATEGOR>E</AUCATEGOR>
    <AUNOMBRE>b. campderrich</AUNOMBRE>
    <AUMATERIA></AUMATERIA>
    <AUNOTAS></AUNOTAS>
    <AUDIRECC></AUDIRECC>
    <AUTELEFONO></AUTELEFONO>
    <AULOCALI></AULOCALI>
    <AUPAIS></AUPAIS>
    <AUEMAIL></AUEMAIL>
    <AUURL></AUURL>
  </Record>
  <Record>
    <AUCATEGOR>E</AUCATEGOR>
    <AUNOMBRE>d.s.i.c.</AUNOMBRE>
    <AUMATERIA></AUMATERIA>
    <AUNOTAS></AUNOTAS>
    <AUDIRECC></AUDIRECC>
    <AUTELEFONO></AUTELEFONO>
    <AULOCALI></AULOCALI>
    <AUPAIS></AUPAIS>
    <AUEMAIL></AUEMAIL>
    <AUURL></AUURL>
  </Record>
  <Record>
    <AUCATEGOR>E</AUCATEGOR>
    <AUNOMBRE>v. hamacher</AUNOMBRE>
    <AUMATERIA></AUMATERIA>
    <AUNOTAS></AUNOTAS>
    <AUDIRECC></AUDIRECC>
    <AUTELEFONO></AUTELEFONO>
    <AULOCALI></AULOCALI>
    <AUPAIS></AUPAIS>
    <AUEMAIL></AUEMAIL>
    <AUURL></AUURL>
  </Record>
  <Record>
    <AUCATEGOR>E</AUCATEGOR>
    <AUNOMBRE>c. smith</AUNOMBRE>
    <AUMATERIA></AUMATERIA>
    <AUNOTAS></AUNOTAS>
    <AUDIRECC></AUDIRECC>
    <AUTELEFONO></AUTELEFONO>
    <AULOCALI></AULOCALI>
    <AUPAIS></AUPAIS>
    <AUEMAIL></AUEMAIL>
    <AUURL></AUURL>
  </Record>
  <Record>
    <AUCATEGOR>E</AUCATEGOR>
    <AUNOMBRE>umberto eco</AUNOMBRE>
    <AUMATERIA></AUMATERIA>
    <AUNOTAS></AUNOTAS>
    <AUDIRECC></AUDIRECC>
    <AUTELEFONO></AUTELEFONO>
    <AULOCALI></AULOCALI>
    <AUPAIS></AUPAIS>
    <AUEMAIL></AUEMAIL>
    <AUURL></AUURL>
  </Record>
  <Record>
    <AUCATEGOR>E</AUCATEGOR>
    <AUNOMBRE>patrick sÜskind</AUNOMBRE>
    <AUMATERIA></AUMATERIA>
    <AUNOTAS></AUNOTAS>
    <AUDIRECC></AUDIRECC>
    <AUTELEFONO></AUTELEFONO>
    <AULOCALI></AULOCALI>
    <AUPAIS></AUPAIS>
    <AUEMAIL></AUEMAIL>
    <AUURL></AUURL>
  </Record>
  <Record>
    <AUCATEGOR>E</AUCATEGOR>
    <AUNOMBRE>milan kundera</AUNOMBRE>
    <AUMATERIA></AUMATERIA>
    <AUNOTAS></AUNOTAS>
    <AUDIRECC></AUDIRECC>
    <AUTELEFONO></AUTELEFONO>
    <AULOCALI></AULOCALI>
    <AUPAIS></AUPAIS>
    <AUEMAIL></AUEMAIL>
    <AUURL></AUURL>
  </Record>
  <Record>
    <AUCATEGOR>E</AUCATEGOR>
    <AUNOMBRE>John K. Toole</AUNOMBRE>
    <AUMATERIA></AUMATERIA>
    <AUNOTAS></AUNOTAS>
    <AUDIRECC></AUDIRECC>
    <AUTELEFONO></AUTELEFONO>
    <AULOCALI></AULOCALI>
    <AUPAIS></AUPAIS>
    <AUEMAIL></AUEMAIL>
    <AUURL></AUURL>
  </Record>
  <Record>
    <AUCATEGOR>E</AUCATEGOR>
    <AUNOMBRE>Antonio Gala</AUNOMBRE>
    <AUMATERIA></AUMATERIA>
    <AUNOTAS></AUNOTAS>
    <AUDIRECC></AUDIRECC>
    <AUTELEFONO></AUTELEFONO>
    <AULOCALI></AULOCALI>
    <AUPAIS></AUPAIS>
    <AUEMAIL></AUEMAIL>
    <AUURL></AUURL>
  </Record>
  <Record>
    <AUCATEGOR>E</AUCATEGOR>
    <AUNOMBRE>Marguerite Duras</AUNOMBRE>
    <AUMATERIA></AUMATERIA>
    <AUNOTAS></AUNOTAS>
    <AUDIRECC></AUDIRECC>
    <AUTELEFONO></AUTELEFONO>
    <AULOCALI></AULOCALI>
    <AUPAIS></AUPAIS>
    <AUEMAIL></AUEMAIL>
    <AUURL></AUURL>
  </Record>
  <Record>
    <AUCATEGOR>E</AUCATEGOR>
    <AUNOMBRE>miguel delibes</AUNOMBRE>
    <AUMATERIA></AUMATERIA>
    <AUNOTAS></AUNOTAS>
    <AUDIRECC></AUDIRECC>
    <AUTELEFONO></AUTELEFONO>
    <AULOCALI></AULOCALI>
    <AUPAIS></AUPAIS>
    <AUEMAIL></AUEMAIL>
    <AUURL></AUURL>
  </Record>
  <Record>
    <AUCATEGOR>E</AUCATEGOR>
    <AUNOMBRE>michael ende</AUNOMBRE>
    <AUMATERIA></AUMATERIA>
    <AUNOTAS></AUNOTAS>
    <AUDIRECC></AUDIRECC>
    <AUTELEFONO></AUTELEFONO>
    <AULOCALI></AULOCALI>
    <AUPAIS></AUPAIS>
    <AUEMAIL></AUEMAIL>
    <AUURL></AUURL>
  </Record>
  <Record>
    <AUCATEGOR>E</AUCATEGOR>
    <AUNOMBRE>gonzalo torrente ballester</AUNOMBRE>
    <AUMATERIA></AUMATERIA>
    <AUNOTAS></AUNOTAS>
    <AUDIRECC></AUDIRECC>
    <AUTELEFONO></AUTELEFONO>
    <AULOCALI></AULOCALI>
    <AUPAIS></AUPAIS>
    <AUEMAIL></AUEMAIL>
    <AUURL></AUURL>
  </Record>
  <Record>
    <AUCATEGOR>E</AUCATEGOR>
    <AUNOMBRE>isak dinesen</AUNOMBRE>
    <AUMATERIA></AUMATERIA>
    <AUNOTAS></AUNOTAS>
    <AUDIRECC></AUDIRECC>
    <AUTELEFONO></AUTELEFONO>
    <AULOCALI></AULOCALI>
    <AUPAIS></AUPAIS>
    <AUEMAIL></AUEMAIL>
    <AUURL></AUURL>
  </Record>
  <Record>
    <AUCATEGOR>E</AUCATEGOR>
    <AUNOMBRE>tom sharpe</AUNOMBRE>
    <AUMATERIA></AUMATERIA>
    <AUNOTAS></AUNOTAS>
    <AUDIRECC></AUDIRECC>
    <AUTELEFONO></AUTELEFONO>
    <AULOCALI></AULOCALI>
    <AUPAIS></AUPAIS>
    <AUEMAIL></AUEMAIL>
    <AUURL></AUURL>
  </Record>
  <Record>
    <AUCATEGOR>E</AUCATEGOR>
    <AUNOMBRE>m. vargas llosa</AUNOMBRE>
    <AUMATERIA></AUMATERIA>
    <AUNOTAS></AUNOTAS>
    <AUDIRECC></AUDIRECC>
    <AUTELEFONO></AUTELEFONO>
    <AULOCALI></AULOCALI>
    <AUPAIS></AUPAIS>
    <AUEMAIL></AUEMAIL>
    <AUURL></AUURL>
  </Record>
  <Record>
    <AUCATEGOR>E</AUCATEGOR>
    <AUNOMBRE>tom wolfe</AUNOMBRE>
    <AUMATERIA></AUMATERIA>
    <AUNOTAS></AUNOTAS>
    <AUDIRECC></AUDIRECC>
    <AUTELEFONO></AUTELEFONO>
    <AULOCALI></AULOCALI>
    <AUPAIS></AUPAIS>
    <AUEMAIL></AUEMAIL>
    <AUURL></AUURL>
  </Record>
  <Record>
    <AUCATEGOR>E</AUCATEGOR>
    <AUNOMBRE>patricia highsmith</AUNOMBRE>
    <AUMATERIA></AUMATERIA>
    <AUNOTAS></AUNOTAS>
    <AUDIRECC></AUDIRECC>
    <AUTELEFONO></AUTELEFONO>
    <AULOCALI></AULOCALI>
    <AUPAIS></AUPAIS>
    <AUEMAIL></AUEMAIL>
    <AUURL></AUURL>
  </Record>
  <Record>
    <AUCATEGOR>E</AUCATEGOR>
    <AUNOMBRE>edward m. forster</AUNOMBRE>
    <AUMATERIA></AUMATERIA>
    <AUNOTAS></AUNOTAS>
    <AUDIRECC></AUDIRECC>
    <AUTELEFONO></AUTELEFONO>
    <AULOCALI></AULOCALI>
    <AUPAIS></AUPAIS>
    <AUEMAIL></AUEMAIL>
    <AUURL></AUURL>
  </Record>
  <Record>
    <AUCATEGOR>E</AUCATEGOR>
    <AUNOMBRE>camilo jose cela</AUNOMBRE>
    <AUMATERIA></AUMATERIA>
    <AUNOTAS></AUNOTAS>
    <AUDIRECC></AUDIRECC>
    <AUTELEFONO></AUTELEFONO>
    <AULOCALI></AULOCALI>
    <AUPAIS></AUPAIS>
    <AUEMAIL></AUEMAIL>
    <AUURL></AUURL>
  </Record>
  <Record>
    <AUCATEGOR>E</AUCATEGOR>
    <AUNOMBRE>evelyn waugh</AUNOMBRE>
    <AUMATERIA></AUMATERIA>
    <AUNOTAS></AUNOTAS>
    <AUDIRECC></AUDIRECC>
    <AUTELEFONO></AUTELEFONO>
    <AULOCALI></AULOCALI>
    <AUPAIS></AUPAIS>
    <AUEMAIL></AUEMAIL>
    <AUURL></AUURL>
  </Record>
  <Record>
    <AUCATEGOR>E</AUCATEGOR>
    <AUNOMBRE>Almudena Grandes</AUNOMBRE>
    <AUMATERIA></AUMATERIA>
    <AUNOTAS></AUNOTAS>
    <AUDIRECC></AUDIRECC>
    <AUTELEFONO></AUTELEFONO>
    <AULOCALI></AULOCALI>
    <AUPAIS></AUPAIS>
    <AUEMAIL></AUEMAIL>
    <AUURL></AUURL>
  </Record>
  <Record>
    <AUCATEGOR>E</AUCATEGOR>
    <AUNOMBRE>gÜnter grass</AUNOMBRE>
    <AUMATERIA></AUMATERIA>
    <AUNOTAS></AUNOTAS>
    <AUDIRECC></AUDIRECC>
    <AUTELEFONO></AUTELEFONO>
    <AULOCALI></AULOCALI>
    <AUPAIS></AUPAIS>
    <AUEMAIL></AUEMAIL>
    <AUURL></AUURL>
  </Record>
  <Record>
    <AUCATEGOR>E</AUCATEGOR>
    <AUNOMBRE>Graham Greene</AUNOMBRE>
    <AUMATERIA></AUMATERIA>
    <AUNOTAS></AUNOTAS>
    <AUDIRECC></AUDIRECC>
    <AUTELEFONO></AUTELEFONO>
    <AULOCALI></AULOCALI>
    <AUPAIS></AUPAIS>
    <AUEMAIL></AUEMAIL>
    <AUURL></AUURL>
  </Record>
  <Record>
    <AUCATEGOR>E</AUCATEGOR>
    <AUNOMBRE>José Félix Rábago</AUNOMBRE>
    <AUMATERIA></AUMATERIA>
    <AUNOTAS></AUNOTAS>
    <AUDIRECC></AUDIRECC>
    <AUTELEFONO></AUTELEFONO>
    <AULOCALI></AULOCALI>
    <AUPAIS></AUPAIS>
    <AUEMAIL></AUEMAIL>
    <AUURL></AUURL>
  </Record>
  <Record>
    <AUCATEGOR>E</AUCATEGOR>
    <AUNOMBRE>grupo eidos</AUNOMBRE>
    <AUMATERIA></AUMATERIA>
    <AUNOTAS></AUNOTAS>
    <AUDIRECC></AUDIRECC>
    <AUTELEFONO></AUTELEFONO>
    <AULOCALI></AULOCALI>
    <AUPAIS></AUPAIS>
    <AUEMAIL></AUEMAIL>
    <AUURL></AUURL>
  </Record>
  <Record>
    <AUCATEGOR>E</AUCATEGOR>
    <AUNOMBRE>microsoft press</AUNOMBRE>
    <AUMATERIA></AUMATERIA>
    <AUNOTAS></AUNOTAS>
    <AUDIRECC></AUDIRECC>
    <AUTELEFONO></AUTELEFONO>
    <AULOCALI></AULOCALI>
    <AUPAIS></AUPAIS>
    <AUEMAIL></AUEMAIL>
    <AUURL></AUURL>
  </Record>
  <Record>
    <AUCATEGOR>E</AUCATEGOR>
    <AUNOMBRE>marino posadas</AUNOMBRE>
    <AUMATERIA></AUMATERIA>
    <AUNOTAS></AUNOTAS>
    <AUDIRECC></AUDIRECC>
    <AUTELEFONO></AUTELEFONO>
    <AULOCALI></AULOCALI>
    <AUPAIS></AUPAIS>
    <AUEMAIL></AUEMAIL>
    <AUURL></AUURL>
  </Record>
  <Record>
    <AUCATEGOR>E</AUCATEGOR>
    <AUNOMBRE>r. spence</AUNOMBRE>
    <AUMATERIA></AUMATERIA>
    <AUNOTAS></AUNOTAS>
    <AUDIRECC></AUDIRECC>
    <AUTELEFONO></AUTELEFONO>
    <AULOCALI></AULOCALI>
    <AUPAIS></AUPAIS>
    <AUEMAIL></AUEMAIL>
    <AUURL></AUURL>
  </Record>
  <Record>
    <AUCATEGOR>E</AUCATEGOR>
    <AUNOMBRE>j. barrallo calonge</AUNOMBRE>
    <AUMATERIA></AUMATERIA>
    <AUNOTAS></AUNOTAS>
    <AUDIRECC></AUDIRECC>
    <AUTELEFONO></AUTELEFONO>
    <AULOCALI></AULOCALI>
    <AUPAIS></AUPAIS>
    <AUEMAIL></AUEMAIL>
    <AUURL></AUURL>
  </Record>
  <Record>
    <AUCATEGOR>E</AUCATEGOR>
    <AUNOMBRE>ian sommerville</AUNOMBRE>
    <AUMATERIA></AUMATERIA>
    <AUNOTAS></AUNOTAS>
    <AUDIRECC></AUDIRECC>
    <AUTELEFONO></AUTELEFONO>
    <AULOCALI></AULOCALI>
    <AUPAIS></AUPAIS>
    <AUEMAIL></AUEMAIL>
    <AUURL></AUURL>
  </Record>
  <Record>
    <AUCATEGOR>E</AUCATEGOR>
    <AUNOMBRE>dan d. gutierrez</AUNOMBRE>
    <AUMATERIA></AUMATERIA>
    <AUNOTAS></AUNOTAS>
    <AUDIRECC></AUDIRECC>
    <AUTELEFONO></AUTELEFONO>
    <AULOCALI></AULOCALI>
    <AUPAIS></AUPAIS>
    <AUEMAIL></AUEMAIL>
    <AUURL></AUURL>
  </Record>
  <Record>
    <AUCATEGOR>E</AUCATEGOR>
    <AUNOMBRE>j.a. de la puente</AUNOMBRE>
    <AUMATERIA></AUMATERIA>
    <AUNOTAS></AUNOTAS>
    <AUDIRECC></AUDIRECC>
    <AUTELEFONO></AUTELEFONO>
    <AULOCALI></AULOCALI>
    <AUPAIS></AUPAIS>
    <AUEMAIL></AUEMAIL>
    <AUURL></AUURL>
  </Record>
  <Record>
    <AUCATEGOR>E</AUCATEGOR>
    <AUNOMBRE>s. fernadez sastre</AUNOMBRE>
    <AUMATERIA></AUMATERIA>
    <AUNOTAS></AUNOTAS>
    <AUDIRECC></AUDIRECC>
    <AUTELEFONO></AUTELEFONO>
    <AULOCALI></AULOCALI>
    <AUPAIS></AUPAIS>
    <AUEMAIL></AUEMAIL>
    <AUURL></AUURL>
  </Record>
  <Record>
    <AUCATEGOR>E</AUCATEGOR>
    <AUNOMBRE>f. charte</AUNOMBRE>
    <AUMATERIA></AUMATERIA>
    <AUNOTAS></AUNOTAS>
    <AUDIRECC></AUDIRECC>
    <AUTELEFONO></AUTELEFONO>
    <AULOCALI></AULOCALI>
    <AUPAIS></AUPAIS>
    <AUEMAIL></AUEMAIL>
    <AUURL></AUURL>
  </Record>
  <Record>
    <AUCATEGOR>E</AUCATEGOR>
    <AUNOMBRE>national geographic society</AUNOMBRE>
    <AUMATERIA></AUMATERIA>
    <AUNOTAS></AUNOTAS>
    <AUDIRECC></AUDIRECC>
    <AUTELEFONO></AUTELEFONO>
    <AULOCALI></AULOCALI>
    <AUPAIS></AUPAIS>
    <AUEMAIL></AUEMAIL>
    <AUURL></AUURL>
  </Record>
  <Record>
    <AUCATEGOR>E</AUCATEGOR>
    <AUNOMBRE>the times</AUNOMBRE>
    <AUMATERIA></AUMATERIA>
    <AUNOTAS></AUNOTAS>
    <AUDIRECC></AUDIRECC>
    <AUTELEFONO></AUTELEFONO>
    <AULOCALI></AULOCALI>
    <AUPAIS></AUPAIS>
    <AUEMAIL></AUEMAIL>
    <AUURL></AUURL>
  </Record>
  <Record>
    <AUCATEGOR>E</AUCATEGOR>
    <AUNOMBRE>Orson Scott Card</AUNOMBRE>
    <AUMATERIA></AUMATERIA>
    <AUNOTAS></AUNOTAS>
    <AUDIRECC></AUDIRECC>
    <AUTELEFONO></AUTELEFONO>
    <AULOCALI></AULOCALI>
    <AUPAIS></AUPAIS>
    <AUEMAIL></AUEMAIL>
    <AUURL></AUURL>
  </Record>
  <Record>
    <AUCATEGOR>E</AUCATEGOR>
    <AUNOMBRE>D. Miller</AUNOMBRE>
    <AUMATERIA></AUMATERIA>
    <AUNOTAS></AUNOTAS>
    <AUDIRECC></AUDIRECC>
    <AUTELEFONO></AUTELEFONO>
    <AULOCALI></AULOCALI>
    <AUPAIS></AUPAIS>
    <AUEMAIL></AUEMAIL>
    <AUURL></AUURL>
  </Record>
  <Record>
    <AUCATEGOR>E</AUCATEGOR>
    <AUNOMBRE>Luanne Seymour Cohen</AUNOMBRE>
    <AUMATERIA></AUMATERIA>
    <AUNOTAS></AUNOTAS>
    <AUDIRECC></AUDIRECC>
    <AUTELEFONO></AUTELEFONO>
    <AULOCALI></AULOCALI>
    <AUPAIS></AUPAIS>
    <AUEMAIL></AUEMAIL>
    <AUURL></AUURL>
  </Record>
  <Record>
    <AUCATEGOR>E</AUCATEGOR>
    <AUNOMBRE>Janet Ashford</AUNOMBRE>
    <AUMATERIA></AUMATERIA>
    <AUNOTAS></AUNOTAS>
    <AUDIRECC></AUDIRECC>
    <AUTELEFONO></AUTELEFONO>
    <AULOCALI></AULOCALI>
    <AUPAIS></AUPAIS>
    <AUEMAIL></AUEMAIL>
    <AUURL></AUURL>
  </Record>
  <Record>
    <AUCATEGOR>E</AUCATEGOR>
    <AUNOMBRE>Gary Bouton</AUNOMBRE>
    <AUMATERIA></AUMATERIA>
    <AUNOTAS></AUNOTAS>
    <AUDIRECC></AUDIRECC>
    <AUTELEFONO></AUTELEFONO>
    <AULOCALI></AULOCALI>
    <AUPAIS></AUPAIS>
    <AUEMAIL></AUEMAIL>
    <AUURL></AUURL>
  </Record>
  <Record>
    <AUCATEGOR>E</AUCATEGOR>
    <AUNOMBRE>Jack Davis</AUNOMBRE>
    <AUMATERIA></AUMATERIA>
    <AUNOTAS></AUNOTAS>
    <AUDIRECC></AUDIRECC>
    <AUTELEFONO></AUTELEFONO>
    <AULOCALI></AULOCALI>
    <AUPAIS></AUPAIS>
    <AUEMAIL></AUEMAIL>
    <AUURL></AUURL>
  </Record>
  <Record>
    <AUCATEGOR>E</AUCATEGOR>
    <AUNOMBRE>Katherine Ulrich</AUNOMBRE>
    <AUMATERIA></AUMATERIA>
    <AUNOTAS></AUNOTAS>
    <AUDIRECC></AUDIRECC>
    <AUTELEFONO></AUTELEFONO>
    <AULOCALI></AULOCALI>
    <AUPAIS></AUPAIS>
    <AUEMAIL></AUEMAIL>
    <AUURL></AUURL>
  </Record>
  <Record>
    <AUCATEGOR>E</AUCATEGOR>
    <AUNOMBRE>J. Badenas</AUNOMBRE>
    <AUMATERIA></AUMATERIA>
    <AUNOTAS></AUNOTAS>
    <AUDIRECC></AUDIRECC>
    <AUTELEFONO></AUTELEFONO>
    <AULOCALI></AULOCALI>
    <AUPAIS></AUPAIS>
    <AUEMAIL></AUEMAIL>
    <AUURL></AUURL>
  </Record>
  <Record>
    <AUCATEGOR>E</AUCATEGOR>
    <AUNOMBRE>Adobe Press</AUNOMBRE>
    <AUMATERIA></AUMATERIA>
    <AUNOTAS></AUNOTAS>
    <AUDIRECC></AUDIRECC>
    <AUTELEFONO></AUTELEFONO>
    <AULOCALI></AULOCALI>
    <AUPAIS></AUPAIS>
    <AUEMAIL></AUEMAIL>
    <AUURL></AUURL>
  </Record>
  <Record>
    <AUCATEGOR>E</AUCATEGOR>
    <AUNOMBRE>M. Vazquez Montalban</AUNOMBRE>
    <AUMATERIA></AUMATERIA>
    <AUNOTAS></AUNOTAS>
    <AUDIRECC></AUDIRECC>
    <AUTELEFONO></AUTELEFONO>
    <AULOCALI></AULOCALI>
    <AUPAIS></AUPAIS>
    <AUEMAIL></AUEMAIL>
    <AUURL></AUURL>
  </Record>
  <Record>
    <AUCATEGOR>E</AUCATEGOR>
    <AUNOMBRE>Neal Stephenson</AUNOMBRE>
    <AUMATERIA></AUMATERIA>
    <AUNOTAS></AUNOTAS>
    <AUDIRECC></AUDIRECC>
    <AUTELEFONO></AUTELEFONO>
    <AULOCALI></AULOCALI>
    <AUPAIS></AUPAIS>
    <AUEMAIL></AUEMAIL>
    <AUURL></AUURL>
  </Record>
  <Record>
    <AUCATEGOR>C</AUCATEGOR>
    <AUNOMBRE>Will Ackerman</AUNOMBRE>
    <AUMATERIA></AUMATERIA>
    <AUNOTAS></AUNOTAS>
    <AUDIRECC></AUDIRECC>
    <AUTELEFONO></AUTELEFONO>
    <AULOCALI></AULOCALI>
    <AUPAIS></AUPAIS>
    <AUEMAIL></AUEMAIL>
    <AUURL></AUURL>
  </Record>
  <Record>
    <AUCATEGOR>C</AUCATEGOR>
    <AUNOMBRE>Adiemus</AUNOMBRE>
    <AUMATERIA></AUMATERIA>
    <AUNOTAS></AUNOTAS>
    <AUDIRECC></AUDIRECC>
    <AUTELEFONO></AUTELEFONO>
    <AULOCALI></AULOCALI>
    <AUPAIS></AUPAIS>
    <AUEMAIL></AUEMAIL>
    <AUURL></AUURL>
  </Record>
  <Record>
    <AUCATEGOR>C</AUCATEGOR>
    <AUNOMBRE>America</AUNOMBRE>
    <AUMATERIA></AUMATERIA>
    <AUNOTAS></AUNOTAS>
    <AUDIRECC></AUDIRECC>
    <AUTELEFONO></AUTELEFONO>
    <AULOCALI></AULOCALI>
    <AUPAIS></AUPAIS>
    <AUEMAIL></AUEMAIL>
    <AUURL></AUURL>
  </Record>
  <Record>
    <AUCATEGOR>C</AUCATEGOR>
    <AUNOMBRE>David Arkenstone</AUNOMBRE>
    <AUMATERIA></AUMATERIA>
    <AUNOTAS></AUNOTAS>
    <AUDIRECC></AUDIRECC>
    <AUTELEFONO></AUTELEFONO>
    <AULOCALI></AULOCALI>
    <AUPAIS></AUPAIS>
    <AUEMAIL></AUEMAIL>
    <AUURL></AUURL>
  </Record>
  <Record>
    <AUCATEGOR>C</AUCATEGOR>
    <AUNOMBRE>J. S. Bach</AUNOMBRE>
    <AUMATERIA></AUMATERIA>
    <AUNOTAS></AUNOTAS>
    <AUDIRECC></AUDIRECC>
    <AUTELEFONO></AUTELEFONO>
    <AULOCALI></AULOCALI>
    <AUPAIS></AUPAIS>
    <AUEMAIL></AUEMAIL>
    <AUURL></AUURL>
  </Record>
  <Record>
    <AUCATEGOR>C</AUCATEGOR>
    <AUNOMBRE>J.S. Bach</AUNOMBRE>
    <AUMATERIA></AUMATERIA>
    <AUNOTAS></AUNOTAS>
    <AUDIRECC></AUDIRECC>
    <AUTELEFONO></AUTELEFONO>
    <AULOCALI></AULOCALI>
    <AUPAIS></AUPAIS>
    <AUEMAIL></AUEMAIL>
    <AUURL></AUURL>
  </Record>
  <Record>
    <AUCATEGOR>C</AUCATEGOR>
    <AUNOMBRE>Beethoven</AUNOMBRE>
    <AUMATERIA></AUMATERIA>
    <AUNOTAS></AUNOTAS>
    <AUDIRECC></AUDIRECC>
    <AUTELEFONO></AUTELEFONO>
    <AULOCALI></AULOCALI>
    <AUPAIS></AUPAIS>
    <AUEMAIL></AUEMAIL>
    <AUURL></AUURL>
  </Record>
  <Record>
    <AUCATEGOR>C</AUCATEGOR>
    <AUNOMBRE>La Bottine Souriante</AUNOMBRE>
    <AUMATERIA></AUMATERIA>
    <AUNOTAS></AUNOTAS>
    <AUDIRECC></AUDIRECC>
    <AUTELEFONO></AUTELEFONO>
    <AULOCALI></AULOCALI>
    <AUPAIS></AUPAIS>
    <AUEMAIL></AUEMAIL>
    <AUURL></AUURL>
  </Record>
  <Record>
    <AUCATEGOR>C</AUCATEGOR>
    <AUNOMBRE>Goran Bregovic</AUNOMBRE>
    <AUMATERIA></AUMATERIA>
    <AUNOTAS></AUNOTAS>
    <AUDIRECC></AUDIRECC>
    <AUTELEFONO></AUTELEFONO>
    <AULOCALI></AULOCALI>
    <AUPAIS></AUPAIS>
    <AUEMAIL></AUEMAIL>
    <AUURL></AUURL>
  </Record>
  <Record>
    <AUCATEGOR>C</AUCATEGOR>
    <AUNOMBRE>Garvin Bryars</AUNOMBRE>
    <AUMATERIA></AUMATERIA>
    <AUNOTAS></AUNOTAS>
    <AUDIRECC></AUDIRECC>
    <AUTELEFONO></AUTELEFONO>
    <AULOCALI></AULOCALI>
    <AUPAIS></AUPAIS>
    <AUEMAIL></AUEMAIL>
    <AUURL></AUURL>
  </Record>
  <Record>
    <AUCATEGOR>C</AUCATEGOR>
    <AUNOMBRE>Carlos d´Alessio</AUNOMBRE>
    <AUMATERIA></AUMATERIA>
    <AUNOTAS></AUNOTAS>
    <AUDIRECC></AUDIRECC>
    <AUTELEFONO></AUTELEFONO>
    <AULOCALI></AULOCALI>
    <AUPAIS></AUPAIS>
    <AUEMAIL></AUEMAIL>
    <AUURL></AUURL>
  </Record>
  <Record>
    <AUCATEGOR>C</AUCATEGOR>
    <AUNOMBRE>John Williams</AUNOMBRE>
    <AUMATERIA></AUMATERIA>
    <AUNOTAS></AUNOTAS>
    <AUDIRECC></AUDIRECC>
    <AUTELEFONO></AUTELEFONO>
    <AULOCALI></AULOCALI>
    <AUPAIS></AUPAIS>
    <AUEMAIL></AUEMAIL>
    <AUURL></AUURL>
  </Record>
  <Record>
    <AUCATEGOR>C</AUCATEGOR>
    <AUNOMBRE>Ryuichi Sakamoto</AUNOMBRE>
    <AUMATERIA></AUMATERIA>
    <AUNOTAS></AUNOTAS>
    <AUDIRECC></AUDIRECC>
    <AUTELEFONO></AUTELEFONO>
    <AULOCALI></AULOCALI>
    <AUPAIS></AUPAIS>
    <AUEMAIL></AUEMAIL>
    <AUURL></AUURL>
  </Record>
  <Record>
    <AUCATEGOR>C</AUCATEGOR>
    <AUNOMBRE>Vangelis</AUNOMBRE>
    <AUMATERIA></AUMATERIA>
    <AUNOTAS></AUNOTAS>
    <AUDIRECC></AUDIRECC>
    <AUTELEFONO></AUTELEFONO>
    <AULOCALI></AULOCALI>
    <AUPAIS></AUPAIS>
    <AUEMAIL></AUEMAIL>
    <AUURL></AUURL>
  </Record>
  <Record>
    <AUCATEGOR>C</AUCATEGOR>
    <AUNOMBRE>Enni Morricone</AUNOMBRE>
    <AUMATERIA></AUMATERIA>
    <AUNOTAS></AUNOTAS>
    <AUDIRECC></AUDIRECC>
    <AUTELEFONO></AUTELEFONO>
    <AULOCALI></AULOCALI>
    <AUPAIS></AUPAIS>
    <AUEMAIL></AUEMAIL>
    <AUURL></AUURL>
  </Record>
  <Record>
    <AUCATEGOR>C</AUCATEGOR>
    <AUNOMBRE>Hans Zimmer</AUNOMBRE>
    <AUMATERIA></AUMATERIA>
    <AUNOTAS></AUNOTAS>
    <AUDIRECC></AUDIRECC>
    <AUTELEFONO></AUTELEFONO>
    <AULOCALI></AULOCALI>
    <AUPAIS></AUPAIS>
    <AUEMAIL></AUEMAIL>
    <AUURL></AUURL>
  </Record>
  <Record>
    <AUCATEGOR>C</AUCATEGOR>
    <AUNOMBRE>Dave Grusin</AUNOMBRE>
    <AUMATERIA></AUMATERIA>
    <AUNOTAS></AUNOTAS>
    <AUDIRECC></AUDIRECC>
    <AUTELEFONO></AUTELEFONO>
    <AULOCALI></AULOCALI>
    <AUPAIS></AUPAIS>
    <AUEMAIL></AUEMAIL>
    <AUURL></AUURL>
  </Record>
  <Record>
    <AUCATEGOR>C</AUCATEGOR>
    <AUNOMBRE>Thomas Newman</AUNOMBRE>
    <AUMATERIA></AUMATERIA>
    <AUNOTAS></AUNOTAS>
    <AUDIRECC></AUDIRECC>
    <AUTELEFONO></AUTELEFONO>
    <AULOCALI></AULOCALI>
    <AUPAIS></AUPAIS>
    <AUEMAIL></AUEMAIL>
    <AUURL></AUURL>
  </Record>
  <Record>
    <AUCATEGOR>C</AUCATEGOR>
    <AUNOMBRE>VV.AA.</AUNOMBRE>
    <AUMATERIA></AUMATERIA>
    <AUNOTAS></AUNOTAS>
    <AUDIRECC></AUDIRECC>
    <AUTELEFONO></AUTELEFONO>
    <AULOCALI></AULOCALI>
    <AUPAIS></AUPAIS>
    <AUEMAIL></AUEMAIL>
    <AUURL></AUURL>
  </Record>
  <Record>
    <AUCATEGOR>C</AUCATEGOR>
    <AUNOMBRE>Camerata Meiga</AUNOMBRE>
    <AUMATERIA></AUMATERIA>
    <AUNOTAS></AUNOTAS>
    <AUDIRECC></AUDIRECC>
    <AUTELEFONO></AUTELEFONO>
    <AULOCALI></AULOCALI>
    <AUPAIS></AUPAIS>
    <AUEMAIL></AUEMAIL>
    <AUURL></AUURL>
  </Record>
  <Record>
    <AUCATEGOR>C</AUCATEGOR>
    <AUNOMBRE>Capercaillie</AUNOMBRE>
    <AUMATERIA></AUMATERIA>
    <AUNOTAS></AUNOTAS>
    <AUDIRECC></AUDIRECC>
    <AUTELEFONO></AUTELEFONO>
    <AULOCALI></AULOCALI>
    <AUPAIS></AUPAIS>
    <AUEMAIL></AUEMAIL>
    <AUURL></AUURL>
  </Record>
  <Record>
    <AUCATEGOR>C</AUCATEGOR>
    <AUNOMBRE>Patrick Cassidy</AUNOMBRE>
    <AUMATERIA></AUMATERIA>
    <AUNOTAS></AUNOTAS>
    <AUDIRECC></AUDIRECC>
    <AUTELEFONO></AUTELEFONO>
    <AULOCALI></AULOCALI>
    <AUPAIS></AUPAIS>
    <AUEMAIL></AUEMAIL>
    <AUURL></AUURL>
  </Record>
  <Record>
    <AUCATEGOR>C</AUCATEGOR>
    <AUNOMBRE>Tracy Chapman</AUNOMBRE>
    <AUMATERIA></AUMATERIA>
    <AUNOTAS></AUNOTAS>
    <AUDIRECC></AUDIRECC>
    <AUTELEFONO></AUTELEFONO>
    <AULOCALI></AULOCALI>
    <AUPAIS></AUPAIS>
    <AUEMAIL></AUEMAIL>
    <AUURL></AUURL>
  </Record>
  <Record>
    <AUCATEGOR>C</AUCATEGOR>
    <AUNOMBRE>Cherish the Ladies</AUNOMBRE>
    <AUMATERIA></AUMATERIA>
    <AUNOTAS></AUNOTAS>
    <AUDIRECC></AUDIRECC>
    <AUTELEFONO></AUTELEFONO>
    <AULOCALI></AULOCALI>
    <AUPAIS></AUPAIS>
    <AUEMAIL></AUEMAIL>
    <AUURL></AUURL>
  </Record>
  <Record>
    <AUCATEGOR>C</AUCATEGOR>
    <AUNOMBRE>Craig Chaquico</AUNOMBRE>
    <AUMATERIA></AUMATERIA>
    <AUNOTAS></AUNOTAS>
    <AUDIRECC></AUDIRECC>
    <AUTELEFONO></AUTELEFONO>
    <AULOCALI></AULOCALI>
    <AUPAIS></AUPAIS>
    <AUEMAIL></AUEMAIL>
    <AUURL></AUURL>
  </Record>
  <Record>
    <AUCATEGOR>C</AUCATEGOR>
    <AUNOMBRE>Suzanne Ciani</AUNOMBRE>
    <AUMATERIA></AUMATERIA>
    <AUNOTAS></AUNOTAS>
    <AUDIRECC></AUDIRECC>
    <AUTELEFONO></AUTELEFONO>
    <AULOCALI></AULOCALI>
    <AUPAIS></AUPAIS>
    <AUEMAIL></AUEMAIL>
    <AUURL></AUURL>
  </Record>
  <Record>
    <AUCATEGOR>C</AUCATEGOR>
    <AUNOMBRE>Clannad</AUNOMBRE>
    <AUMATERIA></AUMATERIA>
    <AUNOTAS></AUNOTAS>
    <AUDIRECC></AUDIRECC>
    <AUTELEFONO></AUTELEFONO>
    <AULOCALI></AULOCALI>
    <AUPAIS></AUPAIS>
    <AUEMAIL></AUEMAIL>
    <AUURL></AUURL>
  </Record>
  <Record>
    <AUCATEGOR>C</AUCATEGOR>
    <AUNOMBRE>David Antony Clark</AUNOMBRE>
    <AUMATERIA></AUMATERIA>
    <AUNOTAS></AUNOTAS>
    <AUDIRECC></AUDIRECC>
    <AUTELEFONO></AUTELEFONO>
    <AULOCALI></AULOCALI>
    <AUPAIS></AUPAIS>
    <AUEMAIL></AUEMAIL>
    <AUURL></AUURL>
  </Record>
  <Record>
    <AUCATEGOR>C</AUCATEGOR>
    <AUNOMBRE>Anne Clark</AUNOMBRE>
    <AUMATERIA></AUMATERIA>
    <AUNOTAS></AUNOTAS>
    <AUDIRECC></AUDIRECC>
    <AUTELEFONO></AUTELEFONO>
    <AULOCALI></AULOCALI>
    <AUPAIS></AUPAIS>
    <AUEMAIL></AUEMAIL>
    <AUURL></AUURL>
  </Record>
  <Record>
    <AUCATEGOR>C</AUCATEGOR>
    <AUNOMBRE>The Corrs</AUNOMBRE>
    <AUMATERIA></AUMATERIA>
    <AUNOTAS></AUNOTAS>
    <AUDIRECC></AUDIRECC>
    <AUTELEFONO></AUTELEFONO>
    <AULOCALI></AULOCALI>
    <AUPAIS></AUPAIS>
    <AUEMAIL></AUEMAIL>
    <AUURL></AUURL>
  </Record>
  <Record>
    <AUCATEGOR>C</AUCATEGOR>
    <AUNOMBRE>Aly Bain &amp; Phil Cunningham</AUNOMBRE>
    <AUMATERIA></AUMATERIA>
    <AUNOTAS></AUNOTAS>
    <AUDIRECC></AUDIRECC>
    <AUTELEFONO></AUTELEFONO>
    <AULOCALI></AULOCALI>
    <AUPAIS></AUPAIS>
    <AUEMAIL></AUEMAIL>
    <AUURL></AUURL>
  </Record>
  <Record>
    <AUCATEGOR>C</AUCATEGOR>
    <AUNOMBRE>Mychael Danna - Tim Clement</AUNOMBRE>
    <AUMATERIA></AUMATERIA>
    <AUNOTAS></AUNOTAS>
    <AUDIRECC></AUDIRECC>
    <AUTELEFONO></AUTELEFONO>
    <AULOCALI></AULOCALI>
    <AUPAIS></AUPAIS>
    <AUEMAIL></AUEMAIL>
    <AUURL></AUURL>
  </Record>
  <Record>
    <AUCATEGOR>C</AUCATEGOR>
    <AUNOMBRE>Mychael Danna - Jeff Danna</AUNOMBRE>
    <AUMATERIA></AUMATERIA>
    <AUNOTAS></AUNOTAS>
    <AUDIRECC></AUDIRECC>
    <AUTELEFONO></AUTELEFONO>
    <AULOCALI></AULOCALI>
    <AUPAIS></AUPAIS>
    <AUEMAIL></AUEMAIL>
    <AUURL></AUURL>
  </Record>
  <Record>
    <AUCATEGOR>C</AUCATEGOR>
    <AUNOMBRE>Dead Can Dance</AUNOMBRE>
    <AUMATERIA></AUMATERIA>
    <AUNOTAS></AUNOTAS>
    <AUDIRECC></AUDIRECC>
    <AUTELEFONO></AUTELEFONO>
    <AULOCALI></AULOCALI>
    <AUPAIS></AUPAIS>
    <AUEMAIL></AUEMAIL>
    <AUURL></AUURL>
  </Record>
  <Record>
    <AUCATEGOR>C</AUCATEGOR>
    <AUNOMBRE>Deep Forest</AUNOMBRE>
    <AUMATERIA></AUMATERIA>
    <AUNOTAS></AUNOTAS>
    <AUDIRECC></AUDIRECC>
    <AUTELEFONO></AUTELEFONO>
    <AULOCALI></AULOCALI>
    <AUPAIS></AUPAIS>
    <AUEMAIL></AUEMAIL>
    <AUURL></AUURL>
  </Record>
  <Record>
    <AUCATEGOR>C</AUCATEGOR>
    <AUNOMBRE>Bob Dylan</AUNOMBRE>
    <AUMATERIA></AUMATERIA>
    <AUNOTAS></AUNOTAS>
    <AUDIRECC></AUDIRECC>
    <AUTELEFONO></AUTELEFONO>
    <AULOCALI></AULOCALI>
    <AUPAIS></AUPAIS>
    <AUEMAIL></AUEMAIL>
    <AUURL></AUURL>
  </Record>
  <Record>
    <AUCATEGOR>C</AUCATEGOR>
    <AUNOMBRE>Seamus Egan</AUNOMBRE>
    <AUMATERIA></AUMATERIA>
    <AUNOTAS></AUNOTAS>
    <AUDIRECC></AUDIRECC>
    <AUTELEFONO></AUTELEFONO>
    <AULOCALI></AULOCALI>
    <AUPAIS></AUPAIS>
    <AUEMAIL></AUEMAIL>
    <AUURL></AUURL>
  </Record>
  <Record>
    <AUCATEGOR>C</AUCATEGOR>
    <AUNOMBRE>Elementales</AUNOMBRE>
    <AUMATERIA></AUMATERIA>
    <AUNOTAS></AUNOTAS>
    <AUDIRECC></AUDIRECC>
    <AUTELEFONO></AUTELEFONO>
    <AULOCALI></AULOCALI>
    <AUPAIS></AUPAIS>
    <AUEMAIL></AUEMAIL>
    <AUURL></AUURL>
  </Record>
  <Record>
    <AUCATEGOR>C</AUCATEGOR>
    <AUNOMBRE>Brian Eno</AUNOMBRE>
    <AUMATERIA></AUMATERIA>
    <AUNOTAS></AUNOTAS>
    <AUDIRECC></AUDIRECC>
    <AUTELEFONO></AUTELEFONO>
    <AULOCALI></AULOCALI>
    <AUPAIS></AUPAIS>
    <AUEMAIL></AUEMAIL>
    <AUURL></AUURL>
  </Record>
  <Record>
    <AUCATEGOR>C</AUCATEGOR>
    <AUNOMBRE>Enya</AUNOMBRE>
    <AUMATERIA></AUMATERIA>
    <AUNOTAS></AUNOTAS>
    <AUDIRECC></AUDIRECC>
    <AUTELEFONO></AUTELEFONO>
    <AULOCALI></AULOCALI>
    <AUPAIS></AUPAIS>
    <AUEMAIL></AUEMAIL>
    <AUURL></AUURL>
  </Record>
  <Record>
    <AUCATEGOR>C</AUCATEGOR>
    <AUNOMBRE>Steve Erquiaga</AUNOMBRE>
    <AUMATERIA></AUMATERIA>
    <AUNOTAS></AUNOTAS>
    <AUDIRECC></AUDIRECC>
    <AUTELEFONO></AUTELEFONO>
    <AULOCALI></AULOCALI>
    <AUPAIS></AUPAIS>
    <AUEMAIL></AUEMAIL>
    <AUURL></AUURL>
  </Record>
  <Record>
    <AUCATEGOR>C</AUCATEGOR>
    <AUNOMBRE>Cesaria Evora</AUNOMBRE>
    <AUMATERIA></AUMATERIA>
    <AUNOTAS></AUNOTAS>
    <AUDIRECC></AUDIRECC>
    <AUTELEFONO></AUTELEFONO>
    <AULOCALI></AULOCALI>
    <AUPAIS></AUPAIS>
    <AUEMAIL></AUEMAIL>
    <AUURL></AUURL>
  </Record>
  <Record>
    <AUCATEGOR>C</AUCATEGOR>
    <AUNOMBRE>Pascal Gaigne</AUNOMBRE>
    <AUMATERIA></AUMATERIA>
    <AUNOTAS></AUNOTAS>
    <AUDIRECC></AUDIRECC>
    <AUTELEFONO></AUTELEFONO>
    <AULOCALI></AULOCALI>
    <AUPAIS></AUPAIS>
    <AUEMAIL></AUEMAIL>
    <AUURL></AUURL>
  </Record>
  <Record>
    <AUCATEGOR>C</AUCATEGOR>
    <AUNOMBRE>James Galway</AUNOMBRE>
    <AUMATERIA></AUMATERIA>
    <AUNOTAS></AUNOTAS>
    <AUDIRECC></AUDIRECC>
    <AUTELEFONO></AUTELEFONO>
    <AULOCALI></AULOCALI>
    <AUPAIS></AUPAIS>
    <AUEMAIL></AUEMAIL>
    <AUURL></AUURL>
  </Record>
  <Record>
    <AUCATEGOR>C</AUCATEGOR>
    <AUNOMBRE>Jan Garbarek</AUNOMBRE>
    <AUMATERIA></AUMATERIA>
    <AUNOTAS></AUNOTAS>
    <AUDIRECC></AUDIRECC>
    <AUTELEFONO></AUTELEFONO>
    <AULOCALI></AULOCALI>
    <AUPAIS></AUPAIS>
    <AUEMAIL></AUEMAIL>
    <AUURL></AUURL>
  </Record>
  <Record>
    <AUCATEGOR>C</AUCATEGOR>
    <AUNOMBRE>Alex de Grassi</AUNOMBRE>
    <AUMATERIA></AUMATERIA>
    <AUNOTAS></AUNOTAS>
    <AUDIRECC></AUDIRECC>
    <AUTELEFONO></AUTELEFONO>
    <AULOCALI></AULOCALI>
    <AUPAIS></AUPAIS>
    <AUEMAIL></AUEMAIL>
    <AUURL></AUURL>
  </Record>
  <Record>
    <AUCATEGOR>C</AUCATEGOR>
    <AUNOMBRE>Juan Luis Guerra</AUNOMBRE>
    <AUMATERIA></AUMATERIA>
    <AUNOTAS></AUNOTAS>
    <AUDIRECC></AUDIRECC>
    <AUTELEFONO></AUTELEFONO>
    <AULOCALI></AULOCALI>
    <AUPAIS></AUPAIS>
    <AUEMAIL></AUEMAIL>
    <AUURL></AUURL>
  </Record>
  <Record>
    <AUCATEGOR>C</AUCATEGOR>
    <AUNOMBRE>Michael Hedges</AUNOMBRE>
    <AUMATERIA></AUMATERIA>
    <AUNOTAS></AUNOTAS>
    <AUDIRECC></AUDIRECC>
    <AUTELEFONO></AUTELEFONO>
    <AULOCALI></AULOCALI>
    <AUPAIS></AUPAIS>
    <AUEMAIL></AUEMAIL>
    <AUURL></AUURL>
  </Record>
  <Record>
    <AUCATEGOR>C</AUCATEGOR>
    <AUNOMBRE>Patrick o&apos;Hearn</AUNOMBRE>
    <AUMATERIA></AUMATERIA>
    <AUNOTAS></AUNOTAS>
    <AUDIRECC></AUDIRECC>
    <AUTELEFONO></AUTELEFONO>
    <AULOCALI></AULOCALI>
    <AUPAIS></AUPAIS>
    <AUEMAIL></AUEMAIL>
    <AUURL></AUURL>
  </Record>
  <Record>
    <AUCATEGOR>C</AUCATEGOR>
    <AUNOMBRE>Hedningarna</AUNOMBRE>
    <AUMATERIA></AUMATERIA>
    <AUNOTAS></AUNOTAS>
    <AUDIRECC></AUDIRECC>
    <AUTELEFONO></AUTELEFONO>
    <AULOCALI></AULOCALI>
    <AUPAIS></AUPAIS>
    <AUEMAIL></AUEMAIL>
    <AUURL></AUURL>
  </Record>
  <Record>
    <AUCATEGOR>C</AUCATEGOR>
    <AUNOMBRE>Antonio Hernández</AUNOMBRE>
    <AUMATERIA></AUMATERIA>
    <AUNOTAS></AUNOTAS>
    <AUDIRECC></AUDIRECC>
    <AUTELEFONO></AUTELEFONO>
    <AULOCALI></AULOCALI>
    <AUPAIS></AUPAIS>
    <AUEMAIL></AUEMAIL>
    <AUURL></AUURL>
  </Record>
  <Record>
    <AUCATEGOR>C</AUCATEGOR>
    <AUNOMBRE>Angel Illarramendi</AUNOMBRE>
    <AUMATERIA></AUMATERIA>
    <AUNOTAS></AUNOTAS>
    <AUDIRECC></AUDIRECC>
    <AUTELEFONO></AUTELEFONO>
    <AULOCALI></AULOCALI>
    <AUPAIS></AUPAIS>
    <AUEMAIL></AUEMAIL>
    <AUURL></AUURL>
  </Record>
  <Record>
    <AUCATEGOR>C</AUCATEGOR>
    <AUNOMBRE>Mark Isham</AUNOMBRE>
    <AUMATERIA></AUMATERIA>
    <AUNOTAS></AUNOTAS>
    <AUDIRECC></AUDIRECC>
    <AUTELEFONO></AUTELEFONO>
    <AULOCALI></AULOCALI>
    <AUPAIS></AUPAIS>
    <AUEMAIL></AUEMAIL>
    <AUURL></AUURL>
  </Record>
  <Record>
    <AUCATEGOR>C</AUCATEGOR>
    <AUNOMBRE>José Luis Encinas</AUNOMBRE>
    <AUMATERIA></AUMATERIA>
    <AUNOTAS></AUNOTAS>
    <AUDIRECC></AUDIRECC>
    <AUTELEFONO></AUTELEFONO>
    <AULOCALI></AULOCALI>
    <AUPAIS></AUPAIS>
    <AUEMAIL></AUEMAIL>
    <AUURL></AUURL>
  </Record>
  <Record>
    <AUCATEGOR>C</AUCATEGOR>
    <AUNOMBRE>Peter Kater - Carlos Nakai</AUNOMBRE>
    <AUMATERIA></AUMATERIA>
    <AUNOTAS></AUNOTAS>
    <AUDIRECC></AUDIRECC>
    <AUTELEFONO></AUTELEFONO>
    <AULOCALI></AULOCALI>
    <AUPAIS></AUPAIS>
    <AUEMAIL></AUEMAIL>
    <AUURL></AUURL>
  </Record>
  <Record>
    <AUCATEGOR>C</AUCATEGOR>
    <AUNOMBRE>Loreena McKennit</AUNOMBRE>
    <AUMATERIA></AUMATERIA>
    <AUNOTAS></AUNOTAS>
    <AUDIRECC></AUDIRECC>
    <AUTELEFONO></AUTELEFONO>
    <AULOCALI></AULOCALI>
    <AUPAIS></AUPAIS>
    <AUEMAIL></AUEMAIL>
    <AUURL></AUURL>
  </Record>
  <Record>
    <AUCATEGOR>C</AUCATEGOR>
    <AUNOMBRE>Kepa Junquera</AUNOMBRE>
    <AUMATERIA></AUMATERIA>
    <AUNOTAS></AUNOTAS>
    <AUDIRECC></AUDIRECC>
    <AUTELEFONO></AUTELEFONO>
    <AULOCALI></AULOCALI>
    <AUPAIS></AUPAIS>
    <AUEMAIL></AUEMAIL>
    <AUURL></AUURL>
  </Record>
  <Record>
    <AUCATEGOR>C</AUCATEGOR>
    <AUNOMBRE>Ketama</AUNOMBRE>
    <AUMATERIA></AUMATERIA>
    <AUNOTAS></AUNOTAS>
    <AUDIRECC></AUDIRECC>
    <AUTELEFONO></AUTELEFONO>
    <AULOCALI></AULOCALI>
    <AUPAIS></AUPAIS>
    <AUEMAIL></AUEMAIL>
    <AUURL></AUURL>
  </Record>
  <Record>
    <AUCATEGOR>C</AUCATEGOR>
    <AUNOMBRE>Khaled</AUNOMBRE>
    <AUMATERIA></AUMATERIA>
    <AUNOTAS></AUNOTAS>
    <AUDIRECC></AUDIRECC>
    <AUTELEFONO></AUTELEFONO>
    <AULOCALI></AULOCALI>
    <AUPAIS></AUPAIS>
    <AUEMAIL></AUEMAIL>
    <AUURL></AUURL>
  </Record>
  <Record>
    <AUCATEGOR>C</AUCATEGOR>
    <AUNOMBRE>Khenany</AUNOMBRE>
    <AUMATERIA></AUMATERIA>
    <AUNOTAS></AUNOTAS>
    <AUDIRECC></AUDIRECC>
    <AUTELEFONO></AUTELEFONO>
    <AULOCALI></AULOCALI>
    <AUPAIS></AUPAIS>
    <AUEMAIL></AUEMAIL>
    <AUURL></AUURL>
  </Record>
  <Record>
    <AUCATEGOR>C</AUCATEGOR>
    <AUNOMBRE>King&apos;s Singers</AUNOMBRE>
    <AUMATERIA></AUMATERIA>
    <AUNOTAS></AUNOTAS>
    <AUDIRECC></AUDIRECC>
    <AUTELEFONO></AUTELEFONO>
    <AULOCALI></AULOCALI>
    <AUPAIS></AUPAIS>
    <AUEMAIL></AUEMAIL>
    <AUURL></AUURL>
  </Record>
  <Record>
    <AUCATEGOR>C</AUCATEGOR>
    <AUNOMBRE>Kitaro</AUNOMBRE>
    <AUMATERIA></AUMATERIA>
    <AUNOTAS></AUNOTAS>
    <AUDIRECC></AUDIRECC>
    <AUTELEFONO></AUTELEFONO>
    <AULOCALI></AULOCALI>
    <AUPAIS></AUPAIS>
    <AUEMAIL></AUEMAIL>
    <AUURL></AUURL>
  </Record>
  <Record>
    <AUCATEGOR>C</AUCATEGOR>
    <AUNOMBRE>Earl Klugh</AUNOMBRE>
    <AUMATERIA></AUMATERIA>
    <AUNOTAS></AUNOTAS>
    <AUDIRECC></AUDIRECC>
    <AUTELEFONO></AUTELEFONO>
    <AULOCALI></AULOCALI>
    <AUPAIS></AUPAIS>
    <AUEMAIL></AUEMAIL>
    <AUURL></AUURL>
  </Record>
  <Record>
    <AUCATEGOR>C</AUCATEGOR>
    <AUNOMBRE>Rodrigo Leao</AUNOMBRE>
    <AUMATERIA></AUMATERIA>
    <AUNOTAS></AUNOTAS>
    <AUDIRECC></AUDIRECC>
    <AUTELEFONO></AUTELEFONO>
    <AULOCALI></AULOCALI>
    <AUPAIS></AUPAIS>
    <AUEMAIL></AUEMAIL>
    <AUURL></AUURL>
  </Record>
  <Record>
    <AUCATEGOR>C</AUCATEGOR>
    <AUNOMBRE>Lluis llach</AUNOMBRE>
    <AUMATERIA></AUMATERIA>
    <AUNOTAS></AUNOTAS>
    <AUDIRECC></AUDIRECC>
    <AUTELEFONO></AUTELEFONO>
    <AULOCALI></AULOCALI>
    <AUPAIS></AUPAIS>
    <AUEMAIL></AUEMAIL>
    <AUURL></AUURL>
  </Record>
  <Record>
    <AUCATEGOR>C</AUCATEGOR>
    <AUNOMBRE>Lisa Lynne</AUNOMBRE>
    <AUMATERIA></AUMATERIA>
    <AUNOTAS></AUNOTAS>
    <AUDIRECC></AUDIRECC>
    <AUTELEFONO></AUTELEFONO>
    <AULOCALI></AULOCALI>
    <AUPAIS></AUPAIS>
    <AUEMAIL></AUEMAIL>
    <AUURL></AUURL>
  </Record>
  <Record>
    <AUCATEGOR>C</AUCATEGOR>
    <AUNOMBRE>paco de lucia et al.</AUNOMBRE>
    <AUMATERIA></AUMATERIA>
    <AUNOTAS></AUNOTAS>
    <AUDIRECC></AUDIRECC>
    <AUTELEFONO></AUTELEFONO>
    <AULOCALI></AULOCALI>
    <AUPAIS></AUPAIS>
    <AUEMAIL></AUEMAIL>
    <AUURL></AUURL>
  </Record>
  <Record>
    <AUCATEGOR>C</AUCATEGOR>
    <AUNOMBRE>Ray Lynch</AUNOMBRE>
    <AUMATERIA></AUMATERIA>
    <AUNOTAS></AUNOTAS>
    <AUDIRECC></AUDIRECC>
    <AUTELEFONO></AUTELEFONO>
    <AULOCALI></AULOCALI>
    <AUPAIS></AUPAIS>
    <AUEMAIL></AUEMAIL>
    <AUURL></AUURL>
  </Record>
  <Record>
    <AUCATEGOR>C</AUCATEGOR>
    <AUNOMBRE>Madredeus</AUNOMBRE>
    <AUMATERIA></AUMATERIA>
    <AUNOTAS></AUNOTAS>
    <AUDIRECC></AUDIRECC>
    <AUTELEFONO></AUTELEFONO>
    <AULOCALI></AULOCALI>
    <AUPAIS></AUPAIS>
    <AUEMAIL></AUEMAIL>
    <AUURL></AUURL>
  </Record>
  <Record>
    <AUCATEGOR>C</AUCATEGOR>
    <AUNOMBRE>Wim Mertens</AUNOMBRE>
    <AUMATERIA></AUMATERIA>
    <AUNOTAS></AUNOTAS>
    <AUDIRECC></AUDIRECC>
    <AUTELEFONO></AUTELEFONO>
    <AULOCALI></AULOCALI>
    <AUPAIS></AUPAIS>
    <AUEMAIL></AUEMAIL>
    <AUURL></AUURL>
  </Record>
  <Record>
    <AUCATEGOR>C</AUCATEGOR>
    <AUNOMBRE>Tomás San Miguel</AUNOMBRE>
    <AUMATERIA></AUMATERIA>
    <AUNOTAS></AUNOTAS>
    <AUDIRECC></AUDIRECC>
    <AUTELEFONO></AUTELEFONO>
    <AULOCALI></AULOCALI>
    <AUPAIS></AUPAIS>
    <AUEMAIL></AUEMAIL>
    <AUURL></AUURL>
  </Record>
  <Record>
    <AUCATEGOR>C</AUCATEGOR>
    <AUNOMBRE>Tomás Sán Miguel</AUNOMBRE>
    <AUMATERIA></AUMATERIA>
    <AUNOTAS></AUNOTAS>
    <AUDIRECC></AUDIRECC>
    <AUTELEFONO></AUTELEFONO>
    <AULOCALI></AULOCALI>
    <AUPAIS></AUPAIS>
    <AUEMAIL></AUEMAIL>
    <AUURL></AUURL>
  </Record>
  <Record>
    <AUCATEGOR>C</AUCATEGOR>
    <AUNOMBRE>Mísia</AUNOMBRE>
    <AUMATERIA></AUMATERIA>
    <AUNOTAS></AUNOTAS>
    <AUDIRECC></AUDIRECC>
    <AUTELEFONO></AUTELEFONO>
    <AULOCALI></AULOCALI>
    <AUPAIS></AUPAIS>
    <AUEMAIL></AUEMAIL>
    <AUURL></AUURL>
  </Record>
  <Record>
    <AUCATEGOR>C</AUCATEGOR>
    <AUNOMBRE>Milladoiro</AUNOMBRE>
    <AUMATERIA></AUMATERIA>
    <AUNOTAS></AUNOTAS>
    <AUDIRECC></AUDIRECC>
    <AUTELEFONO></AUTELEFONO>
    <AULOCALI></AULOCALI>
    <AUPAIS></AUPAIS>
    <AUEMAIL></AUEMAIL>
    <AUURL></AUURL>
  </Record>
  <Record>
    <AUCATEGOR>C</AUCATEGOR>
    <AUNOMBRE>Mozart</AUNOMBRE>
    <AUMATERIA></AUMATERIA>
    <AUNOTAS></AUNOTAS>
    <AUDIRECC></AUDIRECC>
    <AUTELEFONO></AUTELEFONO>
    <AULOCALI></AULOCALI>
    <AUPAIS></AUPAIS>
    <AUEMAIL></AUEMAIL>
    <AUURL></AUURL>
  </Record>
  <Record>
    <AUCATEGOR>C</AUCATEGOR>
    <AUNOMBRE>Pat Metheny group</AUNOMBRE>
    <AUMATERIA></AUMATERIA>
    <AUNOTAS></AUNOTAS>
    <AUDIRECC></AUDIRECC>
    <AUTELEFONO></AUTELEFONO>
    <AULOCALI></AULOCALI>
    <AUPAIS></AUPAIS>
    <AUEMAIL></AUEMAIL>
    <AUURL></AUURL>
  </Record>
  <Record>
    <AUCATEGOR>C</AUCATEGOR>
    <AUNOMBRE>Nightnoise</AUNOMBRE>
    <AUMATERIA></AUMATERIA>
    <AUNOTAS></AUNOTAS>
    <AUDIRECC></AUDIRECC>
    <AUTELEFONO></AUTELEFONO>
    <AULOCALI></AULOCALI>
    <AUPAIS></AUPAIS>
    <AUEMAIL></AUEMAIL>
    <AUURL></AUURL>
  </Record>
  <Record>
    <AUCATEGOR>C</AUCATEGOR>
    <AUNOMBRE>Chris Norman</AUNOMBRE>
    <AUMATERIA></AUMATERIA>
    <AUNOTAS></AUNOTAS>
    <AUDIRECC></AUDIRECC>
    <AUTELEFONO></AUTELEFONO>
    <AULOCALI></AULOCALI>
    <AUPAIS></AUPAIS>
    <AUEMAIL></AUEMAIL>
    <AUURL></AUURL>
  </Record>
  <Record>
    <AUCATEGOR>C</AUCATEGOR>
    <AUNOMBRE>Carlos Nuñez</AUNOMBRE>
    <AUMATERIA></AUMATERIA>
    <AUNOTAS></AUNOTAS>
    <AUDIRECC></AUDIRECC>
    <AUTELEFONO></AUTELEFONO>
    <AULOCALI></AULOCALI>
    <AUPAIS></AUPAIS>
    <AUEMAIL></AUEMAIL>
    <AUURL></AUURL>
  </Record>
  <Record>
    <AUCATEGOR>C</AUCATEGOR>
    <AUNOMBRE>Michael Nyman</AUNOMBRE>
    <AUMATERIA></AUMATERIA>
    <AUNOTAS></AUNOTAS>
    <AUDIRECC></AUDIRECC>
    <AUTELEFONO></AUTELEFONO>
    <AULOCALI></AULOCALI>
    <AUPAIS></AUPAIS>
    <AUEMAIL></AUEMAIL>
    <AUURL></AUURL>
  </Record>
  <Record>
    <AUCATEGOR>C</AUCATEGOR>
    <AUNOMBRE>Penguin Cafe Orchestra</AUNOMBRE>
    <AUMATERIA></AUMATERIA>
    <AUNOTAS></AUNOTAS>
    <AUDIRECC></AUDIRECC>
    <AUTELEFONO></AUTELEFONO>
    <AULOCALI></AULOCALI>
    <AUPAIS></AUPAIS>
    <AUEMAIL></AUEMAIL>
    <AUURL></AUURL>
  </Record>
  <Record>
    <AUCATEGOR>C</AUCATEGOR>
    <AUNOMBRE>Relativity</AUNOMBRE>
    <AUMATERIA></AUMATERIA>
    <AUNOTAS></AUNOTAS>
    <AUDIRECC></AUDIRECC>
    <AUTELEFONO></AUTELEFONO>
    <AULOCALI></AULOCALI>
    <AUPAIS></AUPAIS>
    <AUEMAIL></AUEMAIL>
    <AUURL></AUURL>
  </Record>
  <Record>
    <AUCATEGOR>C</AUCATEGOR>
    <AUNOMBRE>Noirin Ni Riain</AUNOMBRE>
    <AUMATERIA></AUMATERIA>
    <AUNOTAS></AUNOTAS>
    <AUDIRECC></AUDIRECC>
    <AUTELEFONO></AUTELEFONO>
    <AULOCALI></AULOCALI>
    <AUPAIS></AUPAIS>
    <AUEMAIL></AUEMAIL>
    <AUURL></AUURL>
  </Record>
  <Record>
    <AUCATEGOR>C</AUCATEGOR>
    <AUNOMBRE>Philip Riley</AUNOMBRE>
    <AUMATERIA></AUMATERIA>
    <AUNOTAS></AUNOTAS>
    <AUDIRECC></AUDIRECC>
    <AUTELEFONO></AUTELEFONO>
    <AULOCALI></AULOCALI>
    <AUPAIS></AUPAIS>
    <AUEMAIL></AUEMAIL>
    <AUURL></AUURL>
  </Record>
  <Record>
    <AUCATEGOR>C</AUCATEGOR>
    <AUNOMBRE>Phil Sawyer</AUNOMBRE>
    <AUMATERIA></AUMATERIA>
    <AUNOTAS></AUNOTAS>
    <AUDIRECC></AUDIRECC>
    <AUTELEFONO></AUTELEFONO>
    <AULOCALI></AULOCALI>
    <AUPAIS></AUPAIS>
    <AUEMAIL></AUEMAIL>
    <AUURL></AUURL>
  </Record>
  <Record>
    <AUCATEGOR>C</AUCATEGOR>
    <AUNOMBRE>Oystein Sevag</AUNOMBRE>
    <AUMATERIA></AUMATERIA>
    <AUNOTAS></AUNOTAS>
    <AUDIRECC></AUDIRECC>
    <AUTELEFONO></AUTELEFONO>
    <AULOCALI></AULOCALI>
    <AUPAIS></AUPAIS>
    <AUEMAIL></AUEMAIL>
    <AUURL></AUURL>
  </Record>
  <Record>
    <AUCATEGOR>C</AUCATEGOR>
    <AUNOMBRE>Oystein Sevag &amp; Lakki Patey</AUNOMBRE>
    <AUMATERIA></AUMATERIA>
    <AUNOTAS></AUNOTAS>
    <AUDIRECC></AUDIRECC>
    <AUTELEFONO></AUTELEFONO>
    <AULOCALI></AULOCALI>
    <AUPAIS></AUPAIS>
    <AUEMAIL></AUEMAIL>
    <AUURL></AUURL>
  </Record>
  <Record>
    <AUCATEGOR>C</AUCATEGOR>
    <AUNOMBRE>Sharon Shannon</AUNOMBRE>
    <AUMATERIA></AUMATERIA>
    <AUNOTAS></AUNOTAS>
    <AUDIRECC></AUDIRECC>
    <AUTELEFONO></AUTELEFONO>
    <AULOCALI></AULOCALI>
    <AUPAIS></AUPAIS>
    <AUEMAIL></AUEMAIL>
    <AUURL></AUURL>
  </Record>
  <Record>
    <AUCATEGOR>C</AUCATEGOR>
    <AUNOMBRE>Ravi Shankar</AUNOMBRE>
    <AUMATERIA></AUMATERIA>
    <AUNOTAS></AUNOTAS>
    <AUDIRECC></AUDIRECC>
    <AUTELEFONO></AUTELEFONO>
    <AULOCALI></AULOCALI>
    <AUPAIS></AUPAIS>
    <AUEMAIL></AUEMAIL>
    <AUURL></AUURL>
  </Record>
  <Record>
    <AUCATEGOR>C</AUCATEGOR>
    <AUNOMBRE>Chris Spheeris - Paul Voudouris</AUNOMBRE>
    <AUMATERIA></AUMATERIA>
    <AUNOTAS></AUNOTAS>
    <AUDIRECC></AUDIRECC>
    <AUTELEFONO></AUTELEFONO>
    <AULOCALI></AULOCALI>
    <AUPAIS></AUPAIS>
    <AUEMAIL></AUEMAIL>
    <AUURL></AUURL>
  </Record>
  <Record>
    <AUCATEGOR>C</AUCATEGOR>
    <AUNOMBRE>Bruce Sprinsteen</AUNOMBRE>
    <AUMATERIA></AUMATERIA>
    <AUNOTAS></AUNOTAS>
    <AUDIRECC></AUDIRECC>
    <AUTELEFONO></AUTELEFONO>
    <AULOCALI></AULOCALI>
    <AUPAIS></AUPAIS>
    <AUEMAIL></AUEMAIL>
    <AUURL></AUURL>
  </Record>
  <Record>
    <AUCATEGOR>C</AUCATEGOR>
    <AUNOMBRE>Bruce Springsteen</AUNOMBRE>
    <AUMATERIA></AUMATERIA>
    <AUNOTAS></AUNOTAS>
    <AUDIRECC></AUDIRECC>
    <AUTELEFONO></AUTELEFONO>
    <AULOCALI></AULOCALI>
    <AUPAIS></AUPAIS>
    <AUEMAIL></AUEMAIL>
    <AUURL></AUURL>
  </Record>
  <Record>
    <AUCATEGOR>C</AUCATEGOR>
    <AUNOMBRE>Soweto String Quartet</AUNOMBRE>
    <AUMATERIA></AUMATERIA>
    <AUNOTAS></AUNOTAS>
    <AUDIRECC></AUDIRECC>
    <AUTELEFONO></AUTELEFONO>
    <AULOCALI></AULOCALI>
    <AUPAIS></AUPAIS>
    <AUEMAIL></AUEMAIL>
    <AUURL></AUURL>
  </Record>
  <Record>
    <AUCATEGOR>C</AUCATEGOR>
    <AUNOMBRE>Gloria Stefan</AUNOMBRE>
    <AUMATERIA></AUMATERIA>
    <AUNOTAS></AUNOTAS>
    <AUDIRECC></AUDIRECC>
    <AUTELEFONO></AUTELEFONO>
    <AULOCALI></AULOCALI>
    <AUPAIS></AUPAIS>
    <AUEMAIL></AUEMAIL>
    <AUURL></AUURL>
  </Record>
  <Record>
    <AUCATEGOR>C</AUCATEGOR>
    <AUNOMBRE>Alan Stivell</AUNOMBRE>
    <AUMATERIA></AUMATERIA>
    <AUNOTAS></AUNOTAS>
    <AUDIRECC></AUDIRECC>
    <AUTELEFONO></AUTELEFONO>
    <AULOCALI></AULOCALI>
    <AUPAIS></AUPAIS>
    <AUEMAIL></AUEMAIL>
    <AUURL></AUURL>
  </Record>
  <Record>
    <AUCATEGOR>C</AUCATEGOR>
    <AUNOMBRE>Richard Stoltzman</AUNOMBRE>
    <AUMATERIA></AUMATERIA>
    <AUNOTAS></AUNOTAS>
    <AUDIRECC></AUDIRECC>
    <AUTELEFONO></AUTELEFONO>
    <AULOCALI></AULOCALI>
    <AUPAIS></AUPAIS>
    <AUEMAIL></AUEMAIL>
    <AUURL></AUURL>
  </Record>
  <Record>
    <AUCATEGOR>C</AUCATEGOR>
    <AUNOMBRE>Dire Straits</AUNOMBRE>
    <AUMATERIA></AUMATERIA>
    <AUNOTAS></AUNOTAS>
    <AUDIRECC></AUDIRECC>
    <AUTELEFONO></AUTELEFONO>
    <AULOCALI></AULOCALI>
    <AUPAIS></AUPAIS>
    <AUEMAIL></AUEMAIL>
    <AUURL></AUURL>
  </Record>
  <Record>
    <AUCATEGOR>C</AUCATEGOR>
    <AUNOMBRE>Liz Story</AUNOMBRE>
    <AUMATERIA></AUMATERIA>
    <AUNOTAS></AUNOTAS>
    <AUDIRECC></AUDIRECC>
    <AUTELEFONO></AUTELEFONO>
    <AULOCALI></AULOCALI>
    <AUPAIS></AUPAIS>
    <AUEMAIL></AUEMAIL>
    <AUURL></AUURL>
  </Record>
  <Record>
    <AUCATEGOR>C</AUCATEGOR>
    <AUNOMBRE>Andy Summers</AUNOMBRE>
    <AUMATERIA></AUMATERIA>
    <AUNOTAS></AUNOTAS>
    <AUDIRECC></AUDIRECC>
    <AUTELEFONO></AUTELEFONO>
    <AULOCALI></AULOCALI>
    <AUPAIS></AUPAIS>
    <AUEMAIL></AUEMAIL>
    <AUURL></AUURL>
  </Record>
  <Record>
    <AUCATEGOR>C</AUCATEGOR>
    <AUNOMBRE>Tangerine Dream</AUNOMBRE>
    <AUMATERIA></AUMATERIA>
    <AUNOTAS></AUNOTAS>
    <AUDIRECC></AUDIRECC>
    <AUTELEFONO></AUTELEFONO>
    <AULOCALI></AULOCALI>
    <AUPAIS></AUPAIS>
    <AUEMAIL></AUEMAIL>
    <AUURL></AUURL>
  </Record>
  <Record>
    <AUCATEGOR>C</AUCATEGOR>
    <AUNOMBRE>tears for fears</AUNOMBRE>
    <AUMATERIA></AUMATERIA>
    <AUNOTAS></AUNOTAS>
    <AUDIRECC></AUDIRECC>
    <AUTELEFONO></AUTELEFONO>
    <AULOCALI></AULOCALI>
    <AUPAIS></AUPAIS>
    <AUEMAIL></AUEMAIL>
    <AUURL></AUURL>
  </Record>
  <Record>
    <AUCATEGOR>C</AUCATEGOR>
    <AUNOMBRE>Tomita</AUNOMBRE>
    <AUMATERIA></AUMATERIA>
    <AUNOTAS></AUNOTAS>
    <AUDIRECC></AUDIRECC>
    <AUTELEFONO></AUTELEFONO>
    <AULOCALI></AULOCALI>
    <AUPAIS></AUPAIS>
    <AUEMAIL></AUEMAIL>
    <AUURL></AUURL>
  </Record>
  <Record>
    <AUCATEGOR>C</AUCATEGOR>
    <AUNOMBRE>The Tyrel Orchestra</AUNOMBRE>
    <AUMATERIA></AUMATERIA>
    <AUNOTAS></AUNOTAS>
    <AUDIRECC></AUDIRECC>
    <AUTELEFONO></AUTELEFONO>
    <AULOCALI></AULOCALI>
    <AUPAIS></AUPAIS>
    <AUEMAIL></AUEMAIL>
    <AUURL></AUURL>
  </Record>
  <Record>
    <AUCATEGOR>C</AUCATEGOR>
    <AUNOMBRE>Las voces del cielo</AUNOMBRE>
    <AUMATERIA></AUMATERIA>
    <AUNOTAS></AUNOTAS>
    <AUDIRECC></AUDIRECC>
    <AUTELEFONO></AUTELEFONO>
    <AULOCALI></AULOCALI>
    <AUPAIS></AUPAIS>
    <AUEMAIL></AUEMAIL>
    <AUURL></AUURL>
  </Record>
  <Record>
    <AUCATEGOR>C</AUCATEGOR>
    <AUNOMBRE>Green Linnet Artists</AUNOMBRE>
    <AUMATERIA></AUMATERIA>
    <AUNOTAS></AUNOTAS>
    <AUDIRECC></AUDIRECC>
    <AUTELEFONO></AUTELEFONO>
    <AULOCALI></AULOCALI>
    <AUPAIS></AUPAIS>
    <AUEMAIL></AUEMAIL>
    <AUURL></AUURL>
  </Record>
  <Record>
    <AUCATEGOR>C</AUCATEGOR>
    <AUNOMBRE>Hector Vila</AUNOMBRE>
    <AUMATERIA></AUMATERIA>
    <AUNOTAS></AUNOTAS>
    <AUDIRECC></AUDIRECC>
    <AUTELEFONO></AUTELEFONO>
    <AULOCALI></AULOCALI>
    <AUPAIS></AUPAIS>
    <AUEMAIL></AUEMAIL>
    <AUURL></AUURL>
  </Record>
  <Record>
    <AUCATEGOR>C</AUCATEGOR>
    <AUNOMBRE>V.S. Union</AUNOMBRE>
    <AUMATERIA></AUMATERIA>
    <AUNOTAS></AUNOTAS>
    <AUDIRECC></AUDIRECC>
    <AUTELEFONO></AUTELEFONO>
    <AULOCALI></AULOCALI>
    <AUPAIS></AUPAIS>
    <AUEMAIL></AUEMAIL>
    <AUURL></AUURL>
  </Record>
  <Record>
    <AUCATEGOR>C</AUCATEGOR>
    <AUNOMBRE>Varttina</AUNOMBRE>
    <AUMATERIA></AUMATERIA>
    <AUNOTAS></AUNOTAS>
    <AUDIRECC></AUDIRECC>
    <AUTELEFONO></AUTELEFONO>
    <AULOCALI></AULOCALI>
    <AUPAIS></AUPAIS>
    <AUEMAIL></AUEMAIL>
    <AUURL></AUURL>
  </Record>
  <Record>
    <AUCATEGOR>C</AUCATEGOR>
    <AUNOMBRE>VV.AA. Windham Hill</AUNOMBRE>
    <AUMATERIA></AUMATERIA>
    <AUNOTAS></AUNOTAS>
    <AUDIRECC></AUDIRECC>
    <AUTELEFONO></AUTELEFONO>
    <AULOCALI></AULOCALI>
    <AUPAIS></AUPAIS>
    <AUEMAIL></AUEMAIL>
    <AUURL></AUURL>
  </Record>
  <Record>
    <AUCATEGOR>C</AUCATEGOR>
    <AUNOMBRE>Windham Hill Records</AUNOMBRE>
    <AUMATERIA></AUMATERIA>
    <AUNOTAS></AUNOTAS>
    <AUDIRECC></AUDIRECC>
    <AUTELEFONO></AUTELEFONO>
    <AULOCALI></AULOCALI>
    <AUPAIS></AUPAIS>
    <AUEMAIL></AUEMAIL>
    <AUURL></AUURL>
  </Record>
  <Record>
    <AUCATEGOR>C</AUCATEGOR>
    <AUNOMBRE>VV.AA. Whindam Hill</AUNOMBRE>
    <AUMATERIA></AUMATERIA>
    <AUNOTAS></AUNOTAS>
    <AUDIRECC></AUDIRECC>
    <AUTELEFONO></AUTELEFONO>
    <AULOCALI></AULOCALI>
    <AUPAIS></AUPAIS>
    <AUEMAIL></AUEMAIL>
    <AUURL></AUURL>
  </Record>
  <Record>
    <AUCATEGOR>C</AUCATEGOR>
    <AUNOMBRE>VV.AA. Whindham Hill</AUNOMBRE>
    <AUMATERIA></AUMATERIA>
    <AUNOTAS></AUNOTAS>
    <AUDIRECC></AUDIRECC>
    <AUTELEFONO></AUTELEFONO>
    <AULOCALI></AULOCALI>
    <AUPAIS></AUPAIS>
    <AUEMAIL></AUEMAIL>
    <AUURL></AUURL>
  </Record>
  <Record>
    <AUCATEGOR>C</AUCATEGOR>
    <AUNOMBRE>Bill Whelan</AUNOMBRE>
    <AUMATERIA></AUMATERIA>
    <AUNOTAS></AUNOTAS>
    <AUDIRECC></AUDIRECC>
    <AUTELEFONO></AUTELEFONO>
    <AULOCALI></AULOCALI>
    <AUPAIS></AUPAIS>
    <AUEMAIL></AUEMAIL>
    <AUURL></AUURL>
  </Record>
  <Record>
    <AUCATEGOR>C</AUCATEGOR>
    <AUNOMBRE>George Winston</AUNOMBRE>
    <AUMATERIA></AUMATERIA>
    <AUNOTAS></AUNOTAS>
    <AUDIRECC></AUDIRECC>
    <AUTELEFONO></AUTELEFONO>
    <AULOCALI></AULOCALI>
    <AUPAIS></AUPAIS>
    <AUEMAIL></AUEMAIL>
    <AUURL></AUURL>
  </Record>
  <Record>
    <AUCATEGOR>C</AUCATEGOR>
    <AUNOMBRE>Yanni</AUNOMBRE>
    <AUMATERIA></AUMATERIA>
    <AUNOTAS></AUNOTAS>
    <AUDIRECC></AUDIRECC>
    <AUTELEFONO></AUTELEFONO>
    <AULOCALI></AULOCALI>
    <AUPAIS></AUPAIS>
    <AUEMAIL></AUEMAIL>
    <AUURL></AUURL>
  </Record>
  <Record>
    <AUCATEGOR>C</AUCATEGOR>
    <AUNOMBRE>Youssou N´Dour</AUNOMBRE>
    <AUMATERIA></AUMATERIA>
    <AUNOTAS></AUNOTAS>
    <AUDIRECC></AUDIRECC>
    <AUTELEFONO></AUTELEFONO>
    <AULOCALI></AULOCALI>
    <AUPAIS></AUPAIS>
    <AUEMAIL></AUEMAIL>
    <AUURL></AUURL>
  </Record>
  <Record>
    <AUCATEGOR>T</AUCATEGOR>
    <AUNOMBRE>Jocelyn Moorehouse</AUNOMBRE>
    <AUMATERIA></AUMATERIA>
    <AUNOTAS></AUNOTAS>
    <AUDIRECC></AUDIRECC>
    <AUTELEFONO></AUTELEFONO>
    <AULOCALI></AULOCALI>
    <AUPAIS></AUPAIS>
    <AUEMAIL></AUEMAIL>
    <AUURL></AUURL>
  </Record>
  <Record>
    <AUCATEGOR>R</AUCATEGOR>
    <AUNOMBRE>Un actor principal</AUNOMBRE>
    <AUMATERIA></AUMATERIA>
    <AUNOTAS></AUNOTAS>
    <AUDIRECC></AUDIRECC>
    <AUTELEFONO></AUTELEFONO>
    <AULOCALI></AULOCALI>
    <AUPAIS></AUPAIS>
    <AUEMAIL></AUEMAIL>
    <AUURL></AUURL>
  </Record>
  <Record>
    <AUCATEGOR>R</AUCATEGOR>
    <AUNOMBRE>Winona Ryder</AUNOMBRE>
    <AUMATERIA></AUMATERIA>
    <AUNOTAS></AUNOTAS>
    <AUDIRECC></AUDIRECC>
    <AUTELEFONO></AUTELEFONO>
    <AULOCALI></AULOCALI>
    <AUPAIS></AUPAIS>
    <AUEMAIL></AUEMAIL>
    <AUURL></AUURL>
  </Record>
  <Record>
    <AUCATEGOR>T</AUCATEGOR>
    <AUNOMBRE>Pilar Miró</AUNOMBRE>
    <AUMATERIA></AUMATERIA>
    <AUNOTAS></AUNOTAS>
    <AUDIRECC></AUDIRECC>
    <AUTELEFONO></AUTELEFONO>
    <AULOCALI></AULOCALI>
    <AUPAIS></AUPAIS>
    <AUEMAIL></AUEMAIL>
    <AUURL></AUURL>
  </Record>
  <Record>
    <AUCATEGOR>R</AUCATEGOR>
    <AUNOMBRE>Carmelo Gómez</AUNOMBRE>
    <AUMATERIA></AUMATERIA>
    <AUNOTAS></AUNOTAS>
    <AUDIRECC></AUDIRECC>
    <AUTELEFONO></AUTELEFONO>
    <AULOCALI></AULOCALI>
    <AUPAIS></AUPAIS>
    <AUEMAIL></AUEMAIL>
    <AUURL></AUURL>
  </Record>
  <Record>
    <AUCATEGOR>R</AUCATEGOR>
    <AUNOMBRE>Emma Suarez</AUNOMBRE>
    <AUMATERIA></AUMATERIA>
    <AUNOTAS></AUNOTAS>
    <AUDIRECC></AUDIRECC>
    <AUTELEFONO></AUTELEFONO>
    <AULOCALI></AULOCALI>
    <AUPAIS></AUPAIS>
    <AUEMAIL></AUEMAIL>
    <AUURL></AUURL>
  </Record>
  <Record>
    <AUCATEGOR>E</AUCATEGOR>
    <AUNOMBRE>Mark Haddon</AUNOMBRE>
    <AUMATERIA></AUMATERIA>
    <AUNOTAS></AUNOTAS>
    <AUDIRECC></AUDIRECC>
    <AUTELEFONO></AUTELEFONO>
    <AULOCALI></AULOCALI>
    <AUPAIS></AUPAIS>
    <AUEMAIL></AUEMAIL>
    <AUURL></AUURL>
  </Record>
  <Record>
    <AUCATEGOR>E</AUCATEGOR>
    <AUNOMBRE>Fernando Trias de Bes</AUNOMBRE>
    <AUMATERIA></AUMATERIA>
    <AUNOTAS></AUNOTAS>
    <AUDIRECC></AUDIRECC>
    <AUTELEFONO></AUTELEFONO>
    <AULOCALI></AULOCALI>
    <AUPAIS></AUPAIS>
    <AUEMAIL></AUEMAIL>
    <AUURL></AUURL>
  </Record>
  <Record>
    <AUCATEGOR>E</AUCATEGOR>
    <AUNOMBRE>Ed Bott</AUNOMBRE>
    <AUMATERIA></AUMATERIA>
    <AUNOTAS></AUNOTAS>
    <AUDIRECC></AUDIRECC>
    <AUTELEFONO></AUTELEFONO>
    <AULOCALI></AULOCALI>
    <AUPAIS></AUPAIS>
    <AUEMAIL></AUEMAIL>
    <AUURL></AUURL>
  </Record>
  <Record>
    <AUCATEGOR>E</AUCATEGOR>
    <AUNOMBRE>Pedro Manuel Cuenca Jiménez</AUNOMBRE>
    <AUMATERIA></AUMATERIA>
    <AUNOTAS></AUNOTAS>
    <AUDIRECC></AUDIRECC>
    <AUTELEFONO></AUTELEFONO>
    <AULOCALI></AULOCALI>
    <AUPAIS></AUPAIS>
    <AUEMAIL></AUEMAIL>
    <AUURL></AUURL>
  </Record>
  <Record>
    <AUCATEGOR>E</AUCATEGOR>
    <AUNOMBRE>César Martín</AUNOMBRE>
    <AUMATERIA></AUMATERIA>
    <AUNOTAS></AUNOTAS>
    <AUDIRECC></AUDIRECC>
    <AUTELEFONO></AUTELEFONO>
    <AULOCALI></AULOCALI>
    <AUPAIS></AUPAIS>
    <AUEMAIL></AUEMAIL>
    <AUURL></AUURL>
  </Record>
  <Record>
    <AUCATEGOR>E</AUCATEGOR>
    <AUNOMBRE>Alonso Álvarez García</AUNOMBRE>
    <AUMATERIA></AUMATERIA>
    <AUNOTAS></AUNOTAS>
    <AUDIRECC></AUDIRECC>
    <AUTELEFONO></AUTELEFONO>
    <AULOCALI></AULOCALI>
    <AUPAIS></AUPAIS>
    <AUEMAIL></AUEMAIL>
    <AUURL></AUURL>
  </Record>
  <Record>
    <AUCATEGOR>E</AUCATEGOR>
    <AUNOMBRE>Douglas Copland</AUNOMBRE>
    <AUMATERIA></AUMATERIA>
    <AUNOTAS></AUNOTAS>
    <AUDIRECC></AUDIRECC>
    <AUTELEFONO></AUTELEFONO>
    <AULOCALI></AULOCALI>
    <AUPAIS></AUPAIS>
    <AUEMAIL></AUEMAIL>
    <AUURL></AUURL>
  </Record>
  <Record>
    <AUCATEGOR>E</AUCATEGOR>
    <AUNOMBRE>Peter Wayner</AUNOMBRE>
    <AUMATERIA></AUMATERIA>
    <AUNOTAS></AUNOTAS>
    <AUDIRECC></AUDIRECC>
    <AUTELEFONO></AUTELEFONO>
    <AULOCALI></AULOCALI>
    <AUPAIS></AUPAIS>
    <AUEMAIL></AUEMAIL>
    <AUURL></AUURL>
  </Record>
  <Record>
    <AUCATEGOR>E</AUCATEGOR>
    <AUNOMBRE>Martin Davis</AUNOMBRE>
    <AUMATERIA></AUMATERIA>
    <AUNOTAS></AUNOTAS>
    <AUDIRECC></AUDIRECC>
    <AUTELEFONO></AUTELEFONO>
    <AULOCALI></AULOCALI>
    <AUPAIS></AUPAIS>
    <AUEMAIL></AUEMAIL>
    <AUURL></AUURL>
  </Record>
  <Record>
    <AUCATEGOR>E</AUCATEGOR>
    <AUNOMBRE>Donald Norman</AUNOMBRE>
    <AUMATERIA></AUMATERIA>
    <AUNOTAS></AUNOTAS>
    <AUDIRECC></AUDIRECC>
    <AUTELEFONO></AUTELEFONO>
    <AULOCALI></AULOCALI>
    <AUPAIS></AUPAIS>
    <AUEMAIL></AUEMAIL>
    <AUURL></AUURL>
  </Record>
  <Record>
    <AUCATEGOR>E</AUCATEGOR>
    <AUNOMBRE>Ana Martos Rubio</AUNOMBRE>
    <AUMATERIA></AUMATERIA>
    <AUNOTAS></AUNOTAS>
    <AUDIRECC></AUDIRECC>
    <AUTELEFONO></AUTELEFONO>
    <AULOCALI></AULOCALI>
    <AUPAIS></AUPAIS>
    <AUEMAIL></AUEMAIL>
    <AUURL></AUURL>
  </Record>
  <Record>
    <AUCATEGOR>E</AUCATEGOR>
    <AUNOMBRE>Alan F. Chalmers</AUNOMBRE>
    <AUMATERIA>Filosofía de la Ciencia</AUMATERIA>
    <AUNOTAS></AUNOTAS>
    <AUDIRECC></AUDIRECC>
    <AUTELEFONO></AUTELEFONO>
    <AULOCALI></AULOCALI>
    <AUPAIS></AUPAIS>
    <AUEMAIL></AUEMAIL>
    <AUURL></AUURL>
  </Record>
  <Record>
    <AUCATEGOR>E</AUCATEGOR>
    <AUNOMBRE>Michael Lewis</AUNOMBRE>
    <AUMATERIA></AUMATERIA>
    <AUNOTAS></AUNOTAS>
    <AUDIRECC></AUDIRECC>
    <AUTELEFONO></AUTELEFONO>
    <AULOCALI></AULOCALI>
    <AUPAIS></AUPAIS>
    <AUEMAIL></AUEMAIL>
    <AUURL></AUURL>
  </Record>
  <Record>
    <AUCATEGOR>E</AUCATEGOR>
    <AUNOMBRE>Philippe Breton</AUNOMBRE>
    <AUMATERIA></AUMATERIA>
    <AUNOTAS></AUNOTAS>
    <AUDIRECC></AUDIRECC>
    <AUTELEFONO></AUTELEFONO>
    <AULOCALI></AULOCALI>
    <AUPAIS></AUPAIS>
    <AUEMAIL></AUEMAIL>
    <AUURL></AUURL>
  </Record>
  <Record>
    <AUCATEGOR>E</AUCATEGOR>
    <AUNOMBRE>Paul Strathern</AUNOMBRE>
    <AUMATERIA></AUMATERIA>
    <AUNOTAS></AUNOTAS>
    <AUDIRECC></AUDIRECC>
    <AUTELEFONO></AUTELEFONO>
    <AULOCALI></AULOCALI>
    <AUPAIS></AUPAIS>
    <AUEMAIL></AUEMAIL>
    <AUURL></AUURL>
  </Record>
  <Record>
    <AUCATEGOR>E</AUCATEGOR>
    <AUNOMBRE>Nuria Almirón</AUNOMBRE>
    <AUMATERIA></AUMATERIA>
    <AUNOTAS></AUNOTAS>
    <AUDIRECC></AUDIRECC>
    <AUTELEFONO></AUTELEFONO>
    <AULOCALI></AULOCALI>
    <AUPAIS></AUPAIS>
    <AUEMAIL></AUEMAIL>
    <AUURL></AUURL>
  </Record>
  <Record>
    <AUCATEGOR>E</AUCATEGOR>
    <AUNOMBRE>Javier Echevarría</AUNOMBRE>
    <AUMATERIA>Filosofía de la Ciencia</AUMATERIA>
    <AUNOTAS></AUNOTAS>
    <AUDIRECC></AUDIRECC>
    <AUTELEFONO></AUTELEFONO>
    <AULOCALI></AULOCALI>
    <AUPAIS></AUPAIS>
    <AUEMAIL></AUEMAIL>
    <AUURL></AUURL>
  </Record>
  <Record>
    <AUCATEGOR>E</AUCATEGOR>
    <AUNOMBRE>Sherry Turkle</AUNOMBRE>
    <AUMATERIA></AUMATERIA>
    <AUNOTAS></AUNOTAS>
    <AUDIRECC></AUDIRECC>
    <AUTELEFONO></AUTELEFONO>
    <AULOCALI></AULOCALI>
    <AUPAIS></AUPAIS>
    <AUEMAIL></AUEMAIL>
    <AUURL></AUURL>
  </Record>
  <Record>
    <AUCATEGOR>E</AUCATEGOR>
    <AUNOMBRE>Carlos A. Coello Coello</AUNOMBRE>
    <AUMATERIA>Informática/Historia de la</AUMATERIA>
    <AUNOTAS></AUNOTAS>
    <AUDIRECC></AUDIRECC>
    <AUTELEFONO></AUTELEFONO>
    <AULOCALI></AULOCALI>
    <AUPAIS></AUPAIS>
    <AUEMAIL></AUEMAIL>
    <AUURL></AUURL>
  </Record>
  <Record>
    <AUCATEGOR>E</AUCATEGOR>
    <AUNOMBRE>Po Bronson</AUNOMBRE>
    <AUMATERIA></AUMATERIA>
    <AUNOTAS></AUNOTAS>
    <AUDIRECC></AUDIRECC>
    <AUTELEFONO></AUTELEFONO>
    <AULOCALI></AULOCALI>
    <AUPAIS></AUPAIS>
    <AUEMAIL></AUEMAIL>
    <AUURL></AUURL>
  </Record>
  <Record>
    <AUCATEGOR>E</AUCATEGOR>
    <AUNOMBRE>William Aspray</AUNOMBRE>
    <AUMATERIA></AUMATERIA>
    <AUNOTAS></AUNOTAS>
    <AUDIRECC></AUDIRECC>
    <AUTELEFONO></AUTELEFONO>
    <AULOCALI></AULOCALI>
    <AUPAIS></AUPAIS>
    <AUEMAIL></AUEMAIL>
    <AUURL></AUURL>
  </Record>
  <Record>
    <AUCATEGOR>I</AUCATEGOR>
    <AUNOMBRE>Vicentico</AUNOMBRE>
    <AUMATERIA>ROCK LATINO</AUMATERIA>
    <AUNOTAS></AUNOTAS>
    <AUDIRECC></AUDIRECC>
    <AUTELEFONO></AUTELEFONO>
    <AULOCALI></AULOCALI>
    <AUPAIS></AUPAIS>
    <AUEMAIL></AUEMAIL>
    <AUURL></AUURL>
  </Record>
  <Record>
    <AUCATEGOR>C</AUCATEGOR>
    <AUNOMBRE>Vicentico</AUNOMBRE>
    <AUMATERIA></AUMATERIA>
    <AUNOTAS></AUNOTAS>
    <AUDIRECC></AUDIRECC>
    <AUTELEFONO></AUTELEFONO>
    <AULOCALI></AULOCALI>
    <AUPAIS></AUPAIS>
    <AUEMAIL></AUEMAIL>
    <AUURL></AUURL>
  </Record>
  <Record>
    <AUCATEGOR>E</AUCATEGOR>
    <AUNOMBRE>Seth Godin</AUNOMBRE>
    <AUMATERIA>Marketing</AUMATERIA>
    <AUNOTAS></AUNOTAS>
    <AUDIRECC></AUDIRECC>
    <AUTELEFONO></AUTELEFONO>
    <AULOCALI></AULOCALI>
    <AUPAIS></AUPAIS>
    <AUEMAIL></AUEMAIL>
    <AUURL></AUURL>
  </Record>
  <Record>
    <AUCATEGOR>E</AUCATEGOR>
    <AUNOMBRE>Elisabeth Kostova</AUNOMBRE>
    <AUMATERIA>NOVELA</AUMATERIA>
    <AUNOTAS></AUNOTAS>
    <AUDIRECC></AUDIRECC>
    <AUTELEFONO></AUTELEFONO>
    <AULOCALI></AULOCALI>
    <AUPAIS></AUPAIS>
    <AUEMAIL></AUEMAIL>
    <AUURL></AUURL>
  </Record>
  <Record>
    <AUCATEGOR>E</AUCATEGOR>
    <AUNOMBRE>Malcolm Gladwell</AUNOMBRE>
    <AUMATERIA>Sociología</AUMATERIA>
    <AUNOTAS></AUNOTAS>
    <AUDIRECC></AUDIRECC>
    <AUTELEFONO></AUTELEFONO>
    <AULOCALI></AULOCALI>
    <AUPAIS></AUPAIS>
    <AUEMAIL></AUEMAIL>
    <AUURL>http://www.gladwell.com</AUURL>
  </Record>
  <Record>
    <AUCATEGOR>I</AUCATEGOR>
    <AUNOMBRE>VV.AA. Windham Hill</AUNOMBRE>
    <AUMATERIA></AUMATERIA>
    <AUNOTAS></AUNOTAS>
    <AUDIRECC></AUDIRECC>
    <AUTELEFONO></AUTELEFONO>
    <AULOCALI></AULOCALI>
    <AUPAIS></AUPAIS>
    <AUEMAIL></AUEMAIL>
    <AUURL></AUURL>
  </Record>
  <Record>
    <AUCATEGOR>E</AUCATEGOR>
    <AUNOMBRE>Susanna Clarke</AUNOMBRE>
    <AUMATERIA></AUMATERIA>
    <AUNOTAS></AUNOTAS>
    <AUDIRECC></AUDIRECC>
    <AUTELEFONO></AUTELEFONO>
    <AULOCALI></AULOCALI>
    <AUPAIS></AUPAIS>
    <AUEMAIL></AUEMAIL>
    <AUURL></AUURL>
  </Record>
  <Record>
    <AUCATEGOR>E</AUCATEGOR>
    <AUNOMBRE>Hermanos Grimm</AUNOMBRE>
    <AUMATERIA>Cuentos infantiles</AUMATERIA>
    <AUNOTAS></AUNOTAS>
    <AUDIRECC></AUDIRECC>
    <AUTELEFONO></AUTELEFONO>
    <AULOCALI></AULOCALI>
    <AUPAIS></AUPAIS>
    <AUEMAIL></AUEMAIL>
    <AUURL></AUURL>
  </Record>
  <Record>
    <AUCATEGOR>E</AUCATEGOR>
    <AUNOMBRE>Eric Gunnerson</AUNOMBRE>
    <AUMATERIA></AUMATERIA>
    <AUNOTAS></AUNOTAS>
    <AUDIRECC></AUDIRECC>
    <AUTELEFONO></AUTELEFONO>
    <AULOCALI></AULOCALI>
    <AUPAIS></AUPAIS>
    <AUEMAIL></AUEMAIL>
    <AUURL></AUURL>
  </Record>
  <Record>
    <AUCATEGOR>I</AUCATEGOR>
    <AUNOMBRE>Peter Kater - Carlos Nakai</AUNOMBRE>
    <AUMATERIA></AUMATERIA>
    <AUNOTAS></AUNOTAS>
    <AUDIRECC></AUDIRECC>
    <AUTELEFONO></AUTELEFONO>
    <AULOCALI></AULOCALI>
    <AUPAIS></AUPAIS>
    <AUEMAIL></AUEMAIL>
    <AUURL></AUURL>
  </Record>
  <Record>
    <AUCATEGOR>I</AUCATEGOR>
    <AUNOMBRE>VV.AA.</AUNOMBRE>
    <AUMATERIA></AUMATERIA>
    <AUNOTAS></AUNOTAS>
    <AUDIRECC></AUDIRECC>
    <AUTELEFONO></AUTELEFONO>
    <AULOCALI></AULOCALI>
    <AUPAIS></AUPAIS>
    <AUEMAIL></AUEMAIL>
    <AUURL></AUURL>
  </Record>
  <Record>
    <AUCATEGOR>E</AUCATEGOR>
    <AUNOMBRE>Autor nuevo</AUNOMBRE>
    <AUMATERIA></AUMATERIA>
    <AUNOTAS></AUNOTAS>
    <AUDIRECC></AUDIRECC>
    <AUTELEFONO></AUTELEFONO>
    <AULOCALI></AULOCALI>
    <AUPAIS></AUPAIS>
    <AUEMAIL></AUEMAIL>
    <AUURL></AUURL>
  </Record>
  <Record>
    <AUCATEGOR>E</AUCATEGOR>
    <AUNOMBRE>Francisco Charte Ojeda</AUNOMBRE>
    <AUMATERIA></AUMATERIA>
    <AUNOTAS></AUNOTAS>
    <AUDIRECC></AUDIRECC>
    <AUTELEFONO></AUTELEFONO>
    <AULOCALI></AULOCALI>
    <AUPAIS></AUPAIS>
    <AUEMAIL></AUEMAIL>
    <AUURL></AUURL>
  </Record>
  <Record>
    <AUCATEGOR>E</AUCATEGOR>
    <AUNOMBRE>Steven D.Levitt</AUNOMBRE>
    <AUMATERIA></AUMATERIA>
    <AUNOTAS></AUNOTAS>
    <AUDIRECC></AUDIRECC>
    <AUTELEFONO></AUTELEFONO>
    <AULOCALI></AULOCALI>
    <AUPAIS></AUPAIS>
    <AUEMAIL></AUEMAIL>
    <AUURL></AUURL>
  </Record>
  <Record>
    <AUCATEGOR>E</AUCATEGOR>
    <AUNOMBRE>Carl Honoré</AUNOMBRE>
    <AUMATERIA></AUMATERIA>
    <AUNOTAS></AUNOTAS>
    <AUDIRECC></AUDIRECC>
    <AUTELEFONO></AUTELEFONO>
    <AULOCALI></AULOCALI>
    <AUPAIS></AUPAIS>
    <AUEMAIL></AUEMAIL>
    <AUURL></AUURL>
  </Record>
  <Record>
    <AUCATEGOR>E</AUCATEGOR>
    <AUNOMBRE>Thomas Friedman</AUNOMBRE>
    <AUMATERIA></AUMATERIA>
    <AUNOTAS></AUNOTAS>
    <AUDIRECC></AUDIRECC>
    <AUTELEFONO></AUTELEFONO>
    <AULOCALI></AULOCALI>
    <AUPAIS></AUPAIS>
    <AUEMAIL></AUEMAIL>
    <AUURL></AUURL>
  </Record>
  <Record>
    <AUCATEGOR>E</AUCATEGOR>
    <AUNOMBRE>John Boyne</AUNOMBRE>
    <AUMATERIA></AUMATERIA>
    <AUNOTAS></AUNOTAS>
    <AUDIRECC></AUDIRECC>
    <AUTELEFONO></AUTELEFONO>
    <AULOCALI></AULOCALI>
    <AUPAIS></AUPAIS>
    <AUEMAIL></AUEMAIL>
    <AUURL></AUURL>
  </Record>
  <Record>
    <AUCATEGOR>E</AUCATEGOR>
    <AUNOMBRE>Tim Harford</AUNOMBRE>
    <AUMATERIA></AUMATERIA>
    <AUNOTAS></AUNOTAS>
    <AUDIRECC></AUDIRECC>
    <AUTELEFONO></AUTELEFONO>
    <AULOCALI></AULOCALI>
    <AUPAIS></AUPAIS>
    <AUEMAIL></AUEMAIL>
    <AUURL></AUURL>
  </Record>
  <Record>
    <AUCATEGOR>E</AUCATEGOR>
    <AUNOMBRE>Sam Savage</AUNOMBRE>
    <AUMATERIA></AUMATERIA>
    <AUNOTAS></AUNOTAS>
    <AUDIRECC></AUDIRECC>
    <AUTELEFONO></AUTELEFONO>
    <AULOCALI></AULOCALI>
    <AUPAIS></AUPAIS>
    <AUEMAIL></AUEMAIL>
    <AUURL></AUURL>
  </Record>
  <Record>
    <AUCATEGOR>E</AUCATEGOR>
    <AUNOMBRE>Giaconda Belli</AUNOMBRE>
    <AUMATERIA></AUMATERIA>
    <AUNOTAS></AUNOTAS>
    <AUDIRECC></AUDIRECC>
    <AUTELEFONO></AUTELEFONO>
    <AULOCALI></AULOCALI>
    <AUPAIS></AUPAIS>
    <AUEMAIL></AUEMAIL>
    <AUURL></AUURL>
  </Record>
  <Record>
    <AUCATEGOR>E</AUCATEGOR>
    <AUNOMBRE>Anna Gavalda</AUNOMBRE>
    <AUMATERIA></AUMATERIA>
    <AUNOTAS></AUNOTAS>
    <AUDIRECC></AUDIRECC>
    <AUTELEFONO></AUTELEFONO>
    <AULOCALI></AULOCALI>
    <AUPAIS></AUPAIS>
    <AUEMAIL></AUEMAIL>
    <AUURL></AUURL>
  </Record>
</Data>
</ROOT>
